Workbook

Sheet README
A1: Aster & Vale Consumer Products Ltd — Month-End Management Accounts, Working Capital & 13-Week Cash Forecast
A3: Project 3 | Finance operations & management accounting flagship | V1 foundation
A5: Business case
A6: Aster & Vale Consumer Products Ltd is a fictional UK consumer-goods business. The September 2026 month-end requires Finance to close the ledger, post adjustments, reconcile balance-sheet accounts, produce management accounts, assess working capital and maintain a 13-week cash forecast.
A13: V1 workflow
A14: 1 | B14: Load opening TB and ERP-style GL extract
A15: 2 | B15: Map accounts to management-reporting lines
A16: 3 | B16: Post accruals, prepayments, depreciation and bad-debt adjustments
A17: 4 | B17: Produce adjusted trial balance with controls
A18: 5 | B18: Build management P&L and balance sheet
A19: 6 | B19: Reconcile bank, AR and AP
A20: 7 | B20: Calculate DSO, DPO, inventory days and CCC
A21: 8 | B21: Forecast 13 weeks of liquidity
A22: 9 | B22: Track month-end close tasks and unresolved items
A24: Portfolio integrity
A25: All transactions, balances, customer/supplier invoices and assumptions are synthetic. This is an independent portfolio case study and not work completed for a real employer.

Sheet Assumptions
A1: Close, Working Capital & Cash Forecast Assumptions
A5: Cash forecast assumptions
A6: Assumption | B6: Value | C6: Use | D6: Source
A7: Base Weekly Sales (£) | B7: 232000 | C7: Average forecast sales run-rate | D7: Synthetic management assumption
A8: Collection Rate | B8: 0.94 | C8: Share of sales converted to cash in near-term | D8: Synthetic management assumption
A9: Base Weekly COGS (£) | B9: 126000 | C9: Purchasing / supplier cash run-rate | D9: Synthetic management assumption
A10: Supplier Payment Factor | B10: 0.98 | C10: Cash payments vs weekly purchasing | D10: Synthetic management assumption
A11: Monthly Payroll Cash (£) | B11: 215000 | C11: Paid in weeks 4, 8 and 13 | D11: Synthetic management assumption
A12: Monthly Rent (£) | B12: 52000 | C12: Paid in weeks 1, 5, 9 and 13 | D12: Synthetic management assumption
A13: Weekly Other Opex (£) | B13: 27000 | C13: Software, marketing, utilities, travel | D13: Synthetic management assumption
A14: Minimum Cash Policy (£) | B14: 250000 | C14: Liquidity floor | D14: Synthetic treasury assumption
A15: Q4 Capex (£) | B15: 90000 | C15: Split across weeks 6 and 11 | D15: Synthetic capex plan
A16: Q4 Tax / Interest (£) | B16: 60000 | C16: Paid in week 10 | D16: Synthetic treasury assumption

Sheet Chart of Accounts
A1: Chart of Accounts
A3: Account Code | B3: Account Name | C3: Account Type | D3: Management Line | E3: Statement | F3: Normal Balance
A4: 1000 | B4: Bank | C4: Asset | D4: Cash | E4: BS | F4: Debit
A5: 1100 | B5: Trade Receivables | C5: Asset | D5: Trade Receivables | E5: BS | F5: Debit
A6: 1150 | B6: Allowance for Doubtful Debts | C6: Asset | D6: Allowance for Doubtful Debts | E6: BS | F6: Credit
A7: 1200 | B7: Inventory | C7: Asset | D7: Inventory | E7: BS | F7: Debit
A8: 1300 | B8: Prepayments | C8: Asset | D8: Prepayments | E8: BS | F8: Debit
A9: 1400 | B9: Property, Plant & Equipment | C9: Asset | D9: Property, Plant & Equipment | E9: BS | F9: Debit
A10: 1450 | B10: Accumulated Depreciation | C10: Asset | D10: Accumulated Depreciation | E10: BS | F10: Credit
A11: 2000 | B11: Trade Payables | C11: Liability | D11: Trade Payables | E11: BS | F11: Credit
A12: 2100 | B12: Accrued Expenses | C12: Liability | D12: Accrued Expenses | E12: BS | F12: Credit
A13: 2200 | B13: Payroll Liabilities | C13: Liability | D13: Payroll Liabilities | E13: BS | F13: Credit
A14: 2300 | B14: VAT / Tax Payable | C14: Liability | D14: Tax Payable | E14: BS | F14: Credit
... A30: 7000 | B30: Interest Expense | C30: Expense | D30: Interest | E30: PL | F30: Debit

Sheet Opening TB
A1: Opening Trial Balance — 31 Dec 2025
A3: Account Code | B3: Account Name | C3: Opening Balance (£) | D3: Debit (£) | E3: Credit (£) | F3: Source | G3: Control
A4: 1000 | B4: Bank | C4: 450000 | D4: 450000 | E4: 0 | F4: Synthetic opening balance | G4: =D4-E4-C4 -> 0
A5: 1100 | B5: Trade Receivables | C5: 800000 | D5: 800000 | E5: 0 | F5: Synthetic opening balance | G5: =D5-E5-C5 -> 0
A6: 1150 | B6: Allowance for Doubtful Debts | C6: -30000 | D6: 0 | E6: 30000 | F6: Synthetic opening balance | G6: =D6-E6-C6 -> 0
A7: 1200 | B7: Inventory | C7: 650000 | D7: 650000 | E7: 0 | F7: Synthetic opening balance | G7: =D7-E7-C7 -> 0
A8: 1300 | B8: Prepayments | C8: 90000 | D8: 90000 | E8: 0 | F8: Synthetic opening balance | G8: =D8-E8-C8 -> 0
A9: 1400 | B9: Property, Plant & Equipment | C9: 1200000 | D9: 1200000 | E9: 0 | F9: Synthetic opening balance | G9: =D9-E9-C9 -> 0
A10: 1450 | B10: Accumulated Depreciation | C10: -350000 | D10: 0 | E10: 350000 | F10: Synthetic opening balance | G10: =D10-E10-C10 -> 0
A11: 2000 | B11: Trade Payables | C11: -600000 | D11: 0 | E11: 600000 | F11: Synthetic opening balance | G11: =D11-E11-C11 -> 0
A12: 2100 | B12: Accrued Expenses | C12: -150000 | D12: 0 | E12: 150000 | F12: Synthetic opening balance | G12: =D12-E12-C12 -> 0
A13: 2200 | B13: Payroll Liabilities | C13: -60000 | D13: 0 | E13: 60000 | F13: Synthetic opening balance | G13: =D13-E13-C13 -> 0
A14: 2300 | B14: VAT / Tax Payable | C14: -100000 | D14: 0 | E14: 100000 | F14: Synthetic opening balance | G14: =D14-E14-C14 -> 0
A15: 3000 | B15: Share Capital | C15: -500000 | D15: 0 | E15: 500000 | F15: Synthetic opening balance | G15: =D15-E15-C15 -> 0
... A30: 7000 | B30: Interest Expense | C30: 0 | D30: 0 | E30: 0 | F30: Synthetic opening balance | G30: =D30-E30-C30 -> 0
A32: TOTAL | C32: =SUM(C4:C30) -> 0 | D32: =SUM(D4:D30) -> 3190000 | E32: =SUM(E4:E30) -> 3190000 | G32: =D32-E32 -> 0

Sheet GL Extract
A1: ERP General Ledger Extract — Jan to Sep 2026
A3: Journal ID | B3: Date | C3: Account Code | D3: Account Name | E3: Management Line | F3: Statement | G3: Debit (£) | H3: Credit (£) | I3: Net Amount (£) | J3: Reference | K3: Description | L3: Source | M3: Month | N3: Control
A4: JE00001 | B4: 46044 | C4: 1100 | D4: =IFERROR(VLOOKUP(C4,'Chart of Accounts'!$A$4:$F$30,2,FALSE),"") -> Trade Receivables | E4: =IFERROR(VLOOKUP(C4,'Chart of Accounts'!$A$4:$F$30,4,FALSE),"") -> Trade Receivables | F4: =IFERROR(VLOOKUP(C4,'Chart of Accounts'!$A$4:$F$30,5,FALSE),"") -> BS | G4: 47208.301 | H4: 0 | I4: =G4-H4 -> 47208.301 | J4: SI-01-001 | K4: Sales invoice — Customer 29 | L4: Sales Ledger | M4: =TEXT(B4,"yyyy-mm") -> 2026-01 | N4: ="OK" -> OK
A5: JE00001 | B5: 46044 | C5: 4000 | D5: =IFERROR(VLOOKUP(C5,'Chart of Accounts'!$A$4:$F$30,2,FALSE),"") -> Product Sales | E5: =IFERROR(VLOOKUP(C5,'Chart of Accounts'!$A$4:$F$30,4,FALSE),"") -> Revenue | F5: =IFERROR(VLOOKUP(C5,'Chart of Accounts'!$A$4:$F$30,5,FALSE),"") -> PL | G5: 0 | H5: 47208.301 | I5: =G5-H5 -> -47208.301 | J5: SI-01-001 | K5: Sales invoice — Customer 29 | L5: Sales Ledger | M5: =TEXT(B5,"yyyy-mm") -> 2026-01 | N5: ="OK" -> OK
A6: JE00001 | B6: 46044 | C6: 5000 | D6: =IFERROR(VLOOKUP(C6,'Chart of Accounts'!$A$4:$F$30,2,FALSE),"") -> Cost of Goods Sold | E6: =IFERROR(VLOOKUP(C6,'Chart of Accounts'!$A$4:$F$30,4,FALSE),"") -> COGS | F6: =IFERROR(VLOOKUP(C6,'Chart of Accounts'!$A$4:$F$30,5,FALSE),"") -> PL | G6: 26200.607 | H6: 0 | I6: =G6-H6 -> 26200.607 | J6: SI-01-001 | K6: Sales invoice — Customer 29 | L6: Sales Ledger | M6: =TEXT(B6,"yyyy-mm") -> 2026-01 | N6: ="OK" -> OK
A7: JE00001 | B7: 46044 | C7: 1200 | D7: =IFERROR(VLOOKUP(C7,'Chart of Accounts'!$A$4:$F$30,2,FALSE),"") -> Inventory | E7: =IFERROR(VLOOKUP(C7,'Chart of Accounts'!$A$4:$F$30,4,FALSE),"") -> Inventory | F7: =IFERROR(VLOOKUP(C7,'Chart of Accounts'!$A$4:$F$30,5,FALSE),"") -> BS | G7: 0 | H7: 26200.607 | I7: =G7-H7 -> -26200.607 | J7: SI-01-001 | K7: Sales invoice — Customer 29 | L7: Sales Ledger | M7: =TEXT(B7,"yyyy-mm") -> 2026-01 | N7: ="OK" -> OK
A8: JE00002 | B8: 46028 | C8: 1100 | D8: =IFERROR(VLOOKUP(C8,'Chart of Accounts'!$A$4:$F$30,2,FALSE),"") -> Trade Receivables | E8: =IFERROR(VLOOKUP(C8,'Chart of Accounts'!$A$4:$F$30,4,FALSE),"") -> Trade Receivables | F8: =IFERROR(VLOOKUP(C8,'Chart of Accounts'!$A$4:$F$30,5,FALSE),"") -> BS | G8: 91301.083 | H8: 0 | I8: =G8-H8 -> 91301.083 | J8: SI-01-002 | K8: Sales invoice — Customer 27 | L8: Sales Ledger | M8: =TEXT(B8,"yyyy-mm") -> 2026-01 | N8: ="OK" -> OK
A9: JE00002 | B9: 46028 | C9: 4000 | D9: =IFERROR(VLOOKUP(C9,'Chart of Accounts'!$A$4:$F$30,2,FALSE),"") -> Product Sales | E9: =IFERROR(VLOOKUP(C9,'Chart of Accounts'!$A$4:$F$30,4,FALSE),"") -> Revenue | F9: =IFERROR(VLOOKUP(C9,'Chart of Accounts'!$A$4:$F$30,5,FALSE),"") -> PL | G9: 0 | H9: 91301.083 | I9: =G9-H9 -> -91301.083 | J9: SI-01-002 | K9: Sales invoice — Customer 27 | L9: Sales Ledger | M9: =TEXT(B9,"yyyy-mm") -> 2026-01 | N9: ="OK" -> OK
A10: JE00002 | B10: 46028 | C10: 5000 | D10: =IFERROR(VLOOKUP(C10,'Chart of Accounts'!$A$4:$F$30,2,FALSE),"") -> Cost of Goods Sold | E10: =IFERROR(VLOOKUP(C10,'Chart of Accounts'!$A$4:$F$30,4,FALSE),"") -> COGS | F10: =IFERROR(VLOOKUP(C10,'Chart of Accounts'!$A$4:$F$30,5,FALSE),"") -> PL | G10: 50672.101 | H10: 0 | I10: =G10-H10 -> 50672.101 | J10: SI-01-002 | K10: Sales invoice — Customer 27 | L10: Sales Ledger | M10: =TEXT(B10,"yyyy-mm") -> 2026-01 | N10: ="OK" -> OK
A11: JE00002 | B11: 46028 | C11: 1200 | D11: =IFERROR(VLOOKUP(C11,'Chart of Accounts'!$A$4:$F$30,2,FALSE),"") -> Inventory | E11: =IFERROR(VLOOKUP(C11,'Chart of Accounts'!$A$4:$F$30,4,FALSE),"") -> Inventory | F11: =IFERROR(VLOOKUP(C11,'Chart of Accounts'!$A$4:$F$30,5,FALSE),"") -> BS | G11: 0 | H11: 50672.101 | I11: =G11-H11 -> -50672.101 | J11: SI-01-002 | K11: Sales invoice — Customer 27 | L11: Sales Ledger | M11: =TEXT(B11,"yyyy-mm") -> 2026-01 | N11: ="OK" -> OK
A12: JE00003 | B12: 46043 | C12: 1100 | D12: =IFERROR(VLOOKUP(C12,'Chart of Accounts'!$A$4:$F$30,2,FALSE),"") -> Trade Receivables | E12: =IFERROR(VLOOKUP(C12,'Chart of Accounts'!$A$4:$F$30,4,FALSE),"") -> Trade Receivables | F12: =IFERROR(VLOOKUP(C12,'Chart of Accounts'!$A$4:$F$30,5,FALSE),"") -> BS | G12: 62537.911 | H12: 0 | I12: =G12-H12 -> 62537.911 | J12: SI-01-003 | K12: Sales invoice — Customer 17 | L12: Sales Ledger | M12: =TEXT(B12,"yyyy-mm") -> 2026-01 | N12: ="OK" -> OK
A13: JE00003 | B13: 46043 | C13: 4000 | D13: =IFERROR(VLOOKUP(C13,'Chart of Accounts'!$A$4:$F$30,2,FALSE),"") -> Product Sales | E13: =IFERROR(VLOOKUP(C13,'Chart of Accounts'!$A$4:$F$30,4,FALSE),"") -> Revenue | F13: =IFERROR(VLOOKUP(C13,'Chart of Accounts'!$A$4:$F$30,5,FALSE),"") -> PL | G13: 0 | H13: 62537.911 | I13: =G13-H13 -> -62537.911 | J13: SI-01-003 | K13: Sales invoice — Customer 17 | L13: Sales Ledger | M13: =TEXT(B13,"yyyy-mm") -> 2026-01 | N13: ="OK" -> OK
A14: JE00003 | B14: 46043 | C14: 5000 | D14: =IFERROR(VLOOKUP(C14,'Chart of Accounts'!$A$4:$F$30,2,FALSE),"") -> Cost of Goods Sold | E14: =IFERROR(VLOOKUP(C14,'Chart of Accounts'!$A$4:$F$30,4,FALSE),"") -> COGS | F14: =IFERROR(VLOOKUP(C14,'Chart of Accounts'!$A$4:$F$30,5,FALSE),"") -> PL | G14: 34708.541 | H14: 0 | I14: =G14-H14 -> 34708.541 | J14: SI-01-003 | K14: Sales invoice — Customer 17 | L14: Sales Ledger | M14: =TEXT(B14,"yyyy-mm") -> 2026-01 | N14: ="OK" -> OK
A15: JE00003 | B15: 46043 | C15: 1200 | D15: =IFERROR(VLOOKUP(C15,'Chart of Accounts'!$A$4:$F$30,2,FALSE),"") -> Inventory | E15: =IFERROR(VLOOKUP(C15,'Chart of Accounts'!$A$4:$F$30,4,FALSE),"") -> Inventory | F15: =IFERROR(VLOOKUP(C15,'Chart of Accounts'!$A$4:$F$30,5,FALSE),"") -> BS | G15: 0 | H15: 34708.541 | I15: =G15-H15 -> -34708.541 | J15: SI-01-003 | K15: Sales invoice — Customer 17 | L15: Sales Ledger | M15: =TEXT(B15,"yyyy-mm") -> 2026-01 | N15: ="OK" -> OK
... A943: JE00353 | B943: 46193 | C943: 1000 | D943: =IFERROR(VLOOKUP(C943,'Chart of Accounts'!$A$4:$F$30,2,FALSE),"") -> Bank | E943: =IFERROR(VLOOKUP(C943,'Chart of Accounts'!$A$4:$F$30,4,FALSE),"") -> Cash | F943: =IFERROR(VLOOKUP(C943,'Chart of Accounts'!$A$4:$F$30,5,FALSE),"") -> BS | G943: 0 | H943: 65000 | I943: =G943-H943 -> -65000 | J943: TAX-0626 | K943: Corporate tax payment on account | L943: Bank | M943: =TEXT(B943,"yyyy-mm") -> 2026-06 | N943: ="OK" -> OK

Sheet Adjustment Journals
A1: September 2026 Month-End Adjustment Journals
A3: Journal ID | B3: Date | C3: Account Code | D3: Account Name | E3: Management Line | F3: Debit (£) | G3: Credit (£) | H3: Net Amount (£) | I3: Description | J3: Support | K3: Source | L3: Approval
A4: AJ001 | B4: 46295 | C4: 6400 | D4: =IFERROR(VLOOKUP(C4,'Chart of Accounts'!$A$4:$F$30,2,FALSE),"") -> Utilities | E4: =IFERROR(VLOOKUP(C4,'Chart of Accounts'!$A$4:$F$30,4,FALSE),"") -> Utilities | F4: 22000 | G4: 0 | H4: =F4-G4 -> 22000 | I4: Sep utilities accrual | J4: Month-end estimate | K4: Synthetic close assumption | L4: Prepared
A5: AJ001 | B5: 46295 | C5: 2100 | D5: =IFERROR(VLOOKUP(C5,'Chart of Accounts'!$A$4:$F$30,2,FALSE),"") -> Accrued Expenses | E5: =IFERROR(VLOOKUP(C5,'Chart of Accounts'!$A$4:$F$30,4,FALSE),"") -> Accrued Expenses | F5: 0 | G5: 22000 | H5: =F5-G5 -> -22000 | I5: Sep utilities accrual | J5: Month-end estimate | K5: Synthetic close assumption | L5: Prepared
A6: AJ002 | B6: 46295 | C6: 6500 | D6: =IFERROR(VLOOKUP(C6,'Chart of Accounts'!$A$4:$F$30,2,FALSE),"") -> Professional Fees | E6: =IFERROR(VLOOKUP(C6,'Chart of Accounts'!$A$4:$F$30,4,FALSE),"") -> Professional Fees | F6: 18000 | G6: 0 | H6: =F6-G6 -> 18000 | I6: Sep professional fees accrual | J6: Month-end estimate | K6: Synthetic close assumption | L6: Prepared
A7: AJ002 | B7: 46295 | C7: 2100 | D7: =IFERROR(VLOOKUP(C7,'Chart of Accounts'!$A$4:$F$30,2,FALSE),"") -> Accrued Expenses | E7: =IFERROR(VLOOKUP(C7,'Chart of Accounts'!$A$4:$F$30,4,FALSE),"") -> Accrued Expenses | F7: 0 | G7: 18000 | H7: =F7-G7 -> -18000 | I7: Sep professional fees accrual | J7: Month-end estimate | K7: Synthetic close assumption | L7: Prepared
A8: AJ003 | B8: 46295 | C8: 6000 | D8: =IFERROR(VLOOKUP(C8,'Chart of Accounts'!$A$4:$F$30,2,FALSE),"") -> Salaries & Wages | E8: =IFERROR(VLOOKUP(C8,'Chart of Accounts'!$A$4:$F$30,4,FALSE),"") -> Salaries | F8: 35000 | G8: 0 | H8: =F8-G8 -> 35000 | I8: Q3 bonus accrual | J8: HR estimate | K8: Synthetic close assumption | L8: Prepared
A9: AJ003 | B9: 46295 | C9: 2100 | D9: =IFERROR(VLOOKUP(C9,'Chart of Accounts'!$A$4:$F$30,2,FALSE),"") -> Accrued Expenses | E9: =IFERROR(VLOOKUP(C9,'Chart of Accounts'!$A$4:$F$30,4,FALSE),"") -> Accrued Expenses | F9: 0 | G9: 35000 | H9: =F9-G9 -> -35000 | I9: Q3 bonus accrual | J9: HR estimate | K9: Synthetic close assumption | L9: Prepared
A10: AJ004 | B10: 46295 | C10: 6800 | D10: =IFERROR(VLOOKUP(C10,'Chart of Accounts'!$A$4:$F$30,2,FALSE),"") -> Depreciation | E10: =IFERROR(VLOOKUP(C10,'Chart of Accounts'!$A$4:$F$30,4,FALSE),"") -> Depreciation | F10: 15000 | G10: 0 | H10: =F10-G10 -> 15000 | I10: Sep depreciation | J10: Fixed asset schedule | K10: Synthetic close assumption | L10: Prepared
A11: AJ004 | B11: 46295 | C11: 1450 | D11: =IFERROR(VLOOKUP(C11,'Chart of Accounts'!$A$4:$F$30,2,FALSE),"") -> Accumulated Depreciation | E11: =IFERROR(VLOOKUP(C11,'Chart of Accounts'!$A$4:$F$30,4,FALSE),"") -> Accumulated Depreciation | F11: 0 | G11: 15000 | H11: =F11-G11 -> -15000 | I11: Sep depreciation | J11: Fixed asset schedule | K11: Synthetic close assumption | L11: Prepared
A12: AJ005 | B12: 46295 | C12: 1300 | D12: =IFERROR(VLOOKUP(C12,'Chart of Accounts'!$A$4:$F$30,2,FALSE),"") -> Prepayments | E12: =IFERROR(VLOOKUP(C12,'Chart of Accounts'!$A$4:$F$30,4,FALSE),"") -> Prepayments | F12: 24000 | G12: 0 | H12: =F12-G12 -> 24000 | I12: Insurance prepayment Oct-Dec | J12: Prepayment schedule | K12: Synthetic close assumption | L12: Prepared
A13: AJ005 | B13: 46295 | C13: 6550 | D13: =IFERROR(VLOOKUP(C13,'Chart of Accounts'!$A$4:$F$30,2,FALSE),"") -> Insurance | E13: =IFERROR(VLOOKUP(C13,'Chart of Accounts'!$A$4:$F$30,4,FALSE),"") -> Insurance | F13: 0 | G13: 24000 | H13: =F13-G13 -> -24000 | I13: Insurance prepayment Oct-Dec | J13: Prepayment schedule | K13: Synthetic close assumption | L13: Prepared
A14: AJ006 | B14: 46295 | C14: 6900 | D14: =IFERROR(VLOOKUP(C14,'Chart of Accounts'!$A$4:$F$30,2,FALSE),"") -> Bad Debt Expense | E14: =IFERROR(VLOOKUP(C14,'Chart of Accounts'!$A$4:$F$30,4,FALSE),"") -> Bad Debt | F14: 5000 | G14: 0 | H14: =F14-G14 -> 5000 | I14: Increase doubtful debt allowance | J14: AR ageing review | K14: Synthetic close assumption | L14: Prepared
A15: AJ006 | B15: 46295 | C15: 1150 | D15: =IFERROR(VLOOKUP(C15,'Chart of Accounts'!$A$4:$F$30,2,FALSE),"") -> Allowance for Doubtful Debts | E15: =IFERROR(VLOOKUP(C15,'Chart of Accounts'!$A$4:$F$30,4,FALSE),"") -> Allowance for Doubtful Debts | F15: 0 | G15: 5000 | H15: =F15-G15 -> -5000 | I15: Increase doubtful debt allowance | J15: AR ageing review | K15: Synthetic close assumption | L15: Prepared
... A17: AJ007 | B17: 46295 | C17: 2100 | D17: =IFERROR(VLOOKUP(C17,'Chart of Accounts'!$A$4:$F$30,2,FALSE),"") -> Accrued Expenses | E17: =IFERROR(VLOOKUP(C17,'Chart of Accounts'!$A$4:$F$30,4,FALSE),"") -> Accrued Expenses | F17: 0 | G17: 30000 | H17: =F17-G17 -> -30000 | I17: Unbilled marketing campaign | J17: Marketing PO review | K17: Synthetic close assumption | L17: Prepared

Sheet Adjusted TB
A1: Adjusted Trial Balance — 30 Sep 2026
A3: Account Code | B3: Account Name | C3: Type | D3: Management Line | E3: Opening (£) | F3: Base GL (£) | G3: Adjustments (£) | H3: Closing (£) | I3: Debit (£) | J3: Credit (£)
A4: 1000 | B4: Bank | C4: Asset | D4: Cash | E4: =SUMIF('Opening TB'!$A$4:$A$30,A4,'Opening TB'!$C$4:$C$30) -> 450000 | F4: =SUMIF('GL Extract'!$C$4:$C$943,A4,'GL Extract'!$I$4:$I$943) -> 407522.22 | G4: =SUMIF('Adjustment Journals'!$C$4:$C$17,A4,'Adjustment Journals'!$H$4:$H$17) -> 0 | H4: =E4+F4+G4 -> 857522.22 | I4: =MAX(H4,0) -> 857522.22 | J4: =MAX(-H4,0) -> 0
A5: 1100 | B5: Trade Receivables | C5: Asset | D5: Trade Receivables | E5: =SUMIF('Opening TB'!$A$4:$A$30,A5,'Opening TB'!$C$4:$C$30) -> 800000 | F5: =SUMIF('GL Extract'!$C$4:$C$943,A5,'GL Extract'!$I$4:$I$943) -> 351225 | G5: =SUMIF('Adjustment Journals'!$C$4:$C$17,A5,'Adjustment Journals'!$H$4:$H$17) -> 0 | H5: =E5+F5+G5 -> 1151225 | I5: =MAX(H5,0) -> 1151225 | J5: =MAX(-H5,0) -> 0
A6: 1150 | B6: Allowance for Doubtful Debts | C6: Asset | D6: Allowance for Doubtful Debts | E6: =SUMIF('Opening TB'!$A$4:$A$30,A6,'Opening TB'!$C$4:$C$30) -> -30000 | F6: =SUMIF('GL Extract'!$C$4:$C$943,A6,'GL Extract'!$I$4:$I$943) -> 0 | G6: =SUMIF('Adjustment Journals'!$C$4:$C$17,A6,'Adjustment Journals'!$H$4:$H$17) -> -5000 | H6: =E6+F6+G6 -> -35000 | I6: =MAX(H6,0) -> 0 | J6: =MAX(-H6,0) -> 35000
A7: 1200 | B7: Inventory | C7: Asset | D7: Inventory | E7: =SUMIF('Opening TB'!$A$4:$A$30,A7,'Opening TB'!$C$4:$C$30) -> 650000 | F7: =SUMIF('GL Extract'!$C$4:$C$943,A7,'GL Extract'!$I$4:$I$943) -> 10084.8 | G7: =SUMIF('Adjustment Journals'!$C$4:$C$17,A7,'Adjustment Journals'!$H$4:$H$17) -> 0 | H7: =E7+F7+G7 -> 660084.8 | I7: =MAX(H7,0) -> 660084.8 | J7: =MAX(-H7,0) -> 0
A8: 1300 | B8: Prepayments | C8: Asset | D8: Prepayments | E8: =SUMIF('Opening TB'!$A$4:$A$30,A8,'Opening TB'!$C$4:$C$30) -> 90000 | F8: =SUMIF('GL Extract'!$C$4:$C$943,A8,'GL Extract'!$I$4:$I$943) -> 0 | G8: =SUMIF('Adjustment Journals'!$C$4:$C$17,A8,'Adjustment Journals'!$H$4:$H$17) -> 24000 | H8: =E8+F8+G8 -> 114000 | I8: =MAX(H8,0) -> 114000 | J8: =MAX(-H8,0) -> 0
A9: 1400 | B9: Property, Plant & Equipment | C9: Asset | D9: Property, Plant & Equipment | E9: =SUMIF('Opening TB'!$A$4:$A$30,A9,'Opening TB'!$C$4:$C$30) -> 1200000 | F9: =SUMIF('GL Extract'!$C$4:$C$943,A9,'GL Extract'!$I$4:$I$943) -> 230000 | G9: =SUMIF('Adjustment Journals'!$C$4:$C$17,A9,'Adjustment Journals'!$H$4:$H$17) -> 0 | H9: =E9+F9+G9 -> 1430000 | I9: =MAX(H9,0) -> 1430000 | J9: =MAX(-H9,0) -> 0
A10: 1450 | B10: Accumulated Depreciation | C10: Asset | D10: Accumulated Depreciation | E10: =SUMIF('Opening TB'!$A$4:$A$30,A10,'Opening TB'!$C$4:$C$30) -> -350000 | F10: =SUMIF('GL Extract'!$C$4:$C$943,A10,'GL Extract'!$I$4:$I$943) -> -120000 | G10: =SUMIF('Adjustment Journals'!$C$4:$C$17,A10,'Adjustment Journals'!$H$4:$H$17) -> -15000 | H10: =E10+F10+G10 -> -485000 | I10: =MAX(H10,0) -> 0 | J10: =MAX(-H10,0) -> 485000
A11: 2000 | B11: Trade Payables | C11: Liability | D11: Trade Payables | E11: =SUMIF('Opening TB'!$A$4:$A$30,A11,'Opening TB'!$C$4:$C$30) -> -600000 | F11: =SUMIF('GL Extract'!$C$4:$C$943,A11,'GL Extract'!$I$4:$I$943) -> -1039932 | G11: =SUMIF('Adjustment Journals'!$C$4:$C$17,A11,'Adjustment Journals'!$H$4:$H$17) -> 0 | H11: =E11+F11+G11 -> -1639932 | I11: =MAX(H11,0) -> 0 | J11: =MAX(-H11,0) -> 1639932
A12: 2100 | B12: Accrued Expenses | C12: Liability | D12: Accrued Expenses | E12: =SUMIF('Opening TB'!$A$4:$A$30,A12,'Opening TB'!$C$4:$C$30) -> -150000 | F12: =SUMIF('GL Extract'!$C$4:$C$943,A12,'GL Extract'!$I$4:$I$943) -> 0 | G12: =SUMIF('Adjustment Journals'!$C$4:$C$17,A12,'Adjustment Journals'!$H$4:$H$17) -> -105000 | H12: =E12+F12+G12 -> -255000 | I12: =MAX(H12,0) -> 0 | J12: =MAX(-H12,0) -> 255000
A13: 2200 | B13: Payroll Liabilities | C13: Liability | D13: Payroll Liabilities | E13: =SUMIF('Opening TB'!$A$4:$A$30,A13,'Opening TB'!$C$4:$C$30) -> -60000 | F13: =SUMIF('GL Extract'!$C$4:$C$943,A13,'GL Extract'!$I$4:$I$943) -> 0 | G13: =SUMIF('Adjustment Journals'!$C$4:$C$17,A13,'Adjustment Journals'!$H$4:$H$17) -> 0 | H13: =E13+F13+G13 -> -60000 | I13: =MAX(H13,0) -> 0 | J13: =MAX(-H13,0) -> 60000
A14: 2300 | B14: VAT / Tax Payable | C14: Liability | D14: Tax Payable | E14: =SUMIF('Opening TB'!$A$4:$A$30,A14,'Opening TB'!$C$4:$C$30) -> -100000 | F14: =SUMIF('GL Extract'!$C$4:$C$943,A14,'GL Extract'!$I$4:$I$943) -> 65000 | G14: =SUMIF('Adjustment Journals'!$C$4:$C$17,A14,'Adjustment Journals'!$H$4:$H$17) -> 0 | H14: =E14+F14+G14 -> -35000 | I14: =MAX(H14,0) -> 0 | J14: =MAX(-H14,0) -> 35000
A15: 3000 | B15: Share Capital | C15: Equity | D15: Share Capital | E15: =SUMIF('Opening TB'!$A$4:$A$30,A15,'Opening TB'!$C$4:$C$30) -> -500000 | F15: =SUMIF('GL Extract'!$C$4:$C$943,A15,'GL Extract'!$I$4:$I$943) -> 0 | G15: =SUMIF('Adjustment Journals'!$C$4:$C$17,A15,'Adjustment Journals'!$H$4:$H$17) -> 0 | H15: =E15+F15+G15 -> -500000 | I15: =MAX(H15,0) -> 0 | J15: =MAX(-H15,0) -> 500000
... A30: 7000 | B30: Interest Expense | C30: Expense | D30: Interest | E30: =SUMIF('Opening TB'!$A$4:$A$30,A30,'Opening TB'!$C$4:$C$30) -> 0 | F30: =SUMIF('GL Extract'!$C$4:$C$943,A30,'GL Extract'!$I$4:$I$943) -> 49500 | G30: =SUMIF('Adjustment Journals'!$C$4:$C$17,A30,'Adjustment Journals'!$H$4:$H$17) -> 0 | H30: =E30+F30+G30 -> 49500 | I30: =MAX(H30,0) -> 49500 | J30: =MAX(-H30,0) -> 0
A32: TOTAL | E32: =SUM(E4:E30) -> 0 | F32: =SUM(F4:F30) -> -2.6193447e-09 | G32: =SUM(G4:G30) -> 0 | H32: =SUM(H4:H30) -> -2.6193447e-09 | I32: =SUM(I4:I30) -> 12709932 | J32: =SUM(J4:J30) -> 12709932

Sheet Budget
A1: FY2026 Management Budget — Jan to Sep
A3: Management Line | B3: Jan-26 | C3: Feb-26 | D3: Mar-26 | E3: Apr-26 | F3: May-26 | G3: Jun-26 | H3: Jul-26 | I3: Aug-26 | J3: Sep-26 | K3: YTD
A4: Revenue | B4: 805000 | C4: 835000 | D4: 865000 | E4: 895000 | F4: 925000 | G4: 950000 | H4: 965000 | I4: 985000 | J4: 1005000 | K4: 8230000
A5: COGS | B5: 442750 | C5: 459250 | D5: 475750 | E5: 492250 | F5: 508750 | G5: 522500 | H5: 530750 | I5: 541750 | J5: 552750 | K5: 4526500
A6: Salaries | B6: 180000 | C6: 181000 | D6: 182000 | E6: 183000 | F6: 184000 | G6: 186000 | H6: 188000 | I6: 190000 | J6: 192000 | K6: 1666000
A7: Employer Costs | B7: 24300 | C7: 24435 | D7: 24570 | E7: 24705 | F7: 24840 | G7: 25110 | H7: 25380 | I7: 25650 | J7: 25920 | K7: 224910
A8: Marketing | B8: 60000 | C8: 62200 | D8: 64400 | E8: 66600 | F8: 68800 | G8: 71000 | H8: 73200 | I8: 75400 | J8: 77600 | K8: 619200
A9: Rent | B9: 52000 | C9: 52000 | D9: 52000 | E9: 52000 | F9: 52000 | G9: 52000 | H9: 52000 | I9: 52000 | J9: 52000 | K9: 468000
A10: Utilities | B10: 20000 | C10: 20300 | D10: 20600 | E10: 20900 | F10: 21200 | G10: 21500 | H10: 21800 | I10: 22100 | J10: 22400 | K10: 190800
A11: Professional Fees | B11: 14500 | C11: 14950 | D11: 15400 | E11: 15850 | F11: 16300 | G11: 16750 | H11: 17200 | I11: 17650 | J11: 18100 | K11: 146700
A12: Insurance | B12: 8000 | C12: 8000 | D12: 8000 | E12: 8000 | F12: 8000 | G12: 8000 | H12: 8000 | I12: 8000 | J12: 8000 | K12: 72000
A13: Software & IT | B13: 23000 | C13: 23000 | D13: 23000 | E13: 23000 | F13: 23000 | G13: 23000 | H13: 23000 | I13: 23000 | J13: 23000 | K13: 207000
A14: Travel | B14: 8000 | C14: 8250 | D14: 8500 | E14: 8750 | F14: 9000 | G14: 9250 | H14: 9500 | I14: 9750 | J14: 10000 | K14: 81000
A15: Depreciation | B15: 15000 | C15: 15000 | D15: 15000 | E15: 15000 | F15: 15000 | G15: 15000 | H15: 15000 | I15: 15000 | J15: 15000 | K15: 135000
... A17: Interest | B17: 5500 | C17: 5500 | D17: 5500 | E17: 5500 | F17: 5500 | G17: 5500 | H17: 5500 | I17: 5500 | J17: 5500 | K17: 49500

Sheet Management P&L
A1: Management Profit & Loss — Jan to Sep 2026
A3: Management Line | B3: Jan-26 | C3: Feb-26 | D3: Mar-26 | E3: Apr-26 | F3: May-26 | G3: Jun-26 | H3: Jul-26 | I3: Aug-26 | J3: Sep-26 | K3: YTD Actual | L3: YTD Budget | M3: Var £ | N3: Var %
A4: Revenue | B4: =-1*(SUMIFS('GL Extract'!$I$4:$I$943,'GL Extract'!$C$4:$C$943,"4000",'GL Extract'!$B$4:$B$943,">="&DATE(2026,1,1),'GL Extract'!$B$4:$B$943,"<"&DATE(2026,2,1))) -> 820000 | C4: =-1*(SUMIFS('GL Extract'!$I$4:$I$943,'GL Extract'!$C$4:$C$943,"4000",'GL Extract'!$B$4:$B$943,">="&DATE(2026,2,1),'GL Extract'!$B$4:$B$943,"<"&DATE(2026,3,1))) -> 845000 | D4: =-1*(SUMIFS('GL Extract'!$I$4:$I$943,'GL Extract'!$C$4:$C$943,"4000",'GL Extract'!$B$4:$B$943,">="&DATE(2026,3,1),'GL Extract'!$B$4:$B$943,"<"&DATE(2026,4,1))) -> 875000 | E4: =-1*(SUMIFS('GL Extract'!$I$4:$I$943,'GL Extract'!$C$4:$C$943,"4000",'GL Extract'!$B$4:$B$943,">="&DATE(2026,4,1),'GL Extract'!$B$4:$B$943,"<"&DATE(2026,5,1))) -> 900000 | F4: =-1*(SUMIFS('GL Extract'!$I$4:$I$943,'GL Extract'!$C$4:$C$943,"4000",'GL Extract'!$B$4:$B$943,">="&DATE(2026,5,1),'GL Extract'!$B$4:$B$943,"<"&DATE(2026,6,1))) -> 930000 | G4: =-1*(SUMIFS('GL Extract'!$I$4:$I$943,'GL Extract'!$C$4:$C$943,"4000",'GL Extract'!$B$4:$B$943,">="&DATE(2026,6,1),'GL Extract'!$B$4:$B$943,"<"&DATE(2026,7,1))) -> 955000 | H4: =-1*(SUMIFS('GL Extract'!$I$4:$I$943,'GL Extract'!$C$4:$C$943,"4000",'GL Extract'!$B$4:$B$943,">="&DATE(2026,7,1),'GL Extract'!$B$4:$B$943,"<"&DATE(2026,8,1))) -> 970000 | I4: =-1*(SUMIFS('GL Extract'!$I$4:$I$943,'GL Extract'!$C$4:$C$943,"4000",'GL Extract'!$B$4:$B$943,">="&DATE(2026,8,1),'GL Extract'!$B$4:$B$943,"<"&DATE(2026,9,1))) -> 990000 | J4: =-1*(SUMIFS('GL Extract'!$I$4:$I$943,'GL Extract'!$C$4:$C$943,"4000",'GL Extract'!$B$4:$B$943,">="&DATE(2026,9,1),'GL Extract'!$B$4:$B$943,"<"&DATE(2026,10,1))+SUMIF('Adjustment Journals'!$C$4:$C$17,"4000",'Adjustment Journals'!$H$4:$H$17)) -> 1015000 | K4: =SUM(B4:J4) -> 8300000 | L4: =Budget!K4 -> 8230000 | M4: =K4-L4 -> 70000 | N4: =IFERROR(M4/L4,0) -> 0.0085054678
A5: COGS | B5: =1*(SUMIFS('GL Extract'!$I$4:$I$943,'GL Extract'!$C$4:$C$943,"5000",'GL Extract'!$B$4:$B$943,">="&DATE(2026,1,1),'GL Extract'!$B$4:$B$943,"<"&DATE(2026,2,1))) -> 455100 | C5: =1*(SUMIFS('GL Extract'!$I$4:$I$943,'GL Extract'!$C$4:$C$943,"5000",'GL Extract'!$B$4:$B$943,">="&DATE(2026,2,1),'GL Extract'!$B$4:$B$943,"<"&DATE(2026,3,1))) -> 467285 | D5: =1*(SUMIFS('GL Extract'!$I$4:$I$943,'GL Extract'!$C$4:$C$943,"5000",'GL Extract'!$B$4:$B$943,">="&DATE(2026,3,1),'GL Extract'!$B$4:$B$943,"<"&DATE(2026,4,1))) -> 483000 | E5: =1*(SUMIFS('GL Extract'!$I$4:$I$943,'GL Extract'!$C$4:$C$943,"5000",'GL Extract'!$B$4:$B$943,">="&DATE(2026,4,1),'GL Extract'!$B$4:$B$943,"<"&DATE(2026,5,1))) -> 495000 | F5: =1*(SUMIFS('GL Extract'!$I$4:$I$943,'GL Extract'!$C$4:$C$943,"5000",'GL Extract'!$B$4:$B$943,">="&DATE(2026,5,1),'GL Extract'!$B$4:$B$943,"<"&DATE(2026,6,1))) -> 509640 | G5: =1*(SUMIFS('GL Extract'!$I$4:$I$943,'GL Extract'!$C$4:$C$943,"5000",'GL Extract'!$B$4:$B$943,">="&DATE(2026,6,1),'GL Extract'!$B$4:$B$943,"<"&DATE(2026,7,1))) -> 524295 | H5: =1*(SUMIFS('GL Extract'!$I$4:$I$943,'GL Extract'!$C$4:$C$943,"5000",'GL Extract'!$B$4:$B$943,">="&DATE(2026,7,1),'GL Extract'!$B$4:$B$943,"<"&DATE(2026,8,1))) -> 530590 | I5: =1*(SUMIFS('GL Extract'!$I$4:$I$943,'GL Extract'!$C$4:$C$943,"5000",'GL Extract'!$B$4:$B$943,">="&DATE(2026,8,1),'GL Extract'!$B$4:$B$943,"<"&DATE(2026,9,1))) -> 540540 | J5: =1*(SUMIFS('GL Extract'!$I$4:$I$943,'GL Extract'!$C$4:$C$943,"5000",'GL Extract'!$B$4:$B$943,">="&DATE(2026,9,1),'GL Extract'!$B$4:$B$943,"<"&DATE(2026,10,1))+SUMIF('Adjustment Journals'!$C$4:$C$17,"5000",'Adjustment Journals'!$H$4:$H$17)) -> 553175 | K5: =SUM(B5:J5) -> 4558625 | L5: =Budget!K5 -> 4526500 | M5: =K5-L5 -> 32125 | N5: =IFERROR(M5/L5,0) -> 0.0070970949
A6: Gross Profit | B6: =B4-B5 -> 364900 | C6: =C4-C5 -> 377715 | D6: =D4-D5 -> 392000 | E6: =E4-E5 -> 405000 | F6: =F4-F5 -> 420360 | G6: =G4-G5 -> 430705 | H6: =H4-H5 -> 439410 | I6: =I4-I5 -> 449460 | J6: =J4-J5 -> 461825 | K6: =SUM(B6:J6) -> 3741375 | L6: =L4-L5 -> 3703500 | M6: =K6-L6 -> 37875 | N6: =IFERROR(M6/L6,0) -> 0.010226812
A7: Gross Margin % | B7: =IFERROR(B6/B4,0) -> 0.445 | C7: =IFERROR(C6/C4,0) -> 0.447 | D7: =IFERROR(D6/D4,0) -> 0.448 | E7: =IFERROR(E6/E4,0) -> 0.45 | F7: =IFERROR(F6/F4,0) -> 0.452 | G7: =IFERROR(G6/G4,0) -> 0.451 | H7: =IFERROR(H6/H4,0) -> 0.453 | I7: =IFERROR(I6/I4,0) -> 0.454 | ... L7: =IFERROR(L6/L4,0) -> 0.45 | M7: =K7-L7 -> 0.00076807229 | N7: -
A8: Salaries | B8: =1*(SUMIFS('GL Extract'!$I$4:$I$943,'GL Extract'!$C$4:$C$943,"6000",'GL Extract'!$B$4:$B$943,">="&DATE(2026,1,1),'GL Extract'!$B$4:$B$943,"<"&DATE(2026,2,1))) -> 183571.92 | C8: =1*(SUMIFS('GL Extract'!$I$4:$I$943,'GL Extract'!$C$4:$C$943,"6000",'GL Extract'!$B$4:$B$943,">="&DATE(2026,2,1),'GL Extract'!$B$4:$B$943,"<"&DATE(2026,3,1))) -> 180967.2 | D8: =1*(SUMIFS('GL Extract'!$I$4:$I$943,'GL Extract'!$C$4:$C$943,"6000",'GL Extract'!$B$4:$B$943,">="&DATE(2026,3,1),'GL Extract'!$B$4:$B$943,"<"&DATE(2026,4,1))) -> 184387.08 | E8: =1*(SUMIFS('GL Extract'!$I$4:$I$943,'GL Extract'!$C$4:$C$943,"6000",'GL Extract'!$B$4:$B$943,">="&DATE(2026,4,1),'GL Extract'!$B$4:$B$943,"<"&DATE(2026,5,1))) -> 181710.98 | F8: =1*(SUMIFS('GL Extract'!$I$4:$I$943,'GL Extract'!$C$4:$C$943,"6000",'GL Extract'!$B$4:$B$943,">="&DATE(2026,5,1),'GL Extract'!$B$4:$B$943,"<"&DATE(2026,6,1))) -> 185478.46 | G8: =1*(SUMIFS('GL Extract'!$I$4:$I$943,'GL Extract'!$C$4:$C$943,"6000",'GL Extract'!$B$4:$B$943,">="&DATE(2026,6,1),'GL Extract'!$B$4:$B$943,"<"&DATE(2026,7,1))) -> 187666.59 | H8: =1*(SUMIFS('GL Extract'!$I$4:$I$943,'GL Extract'!$C$4:$C$943,"6000",'GL Extract'!$B$4:$B$943,">="&DATE(2026,7,1),'GL Extract'!$B$4:$B$943,"<"&DATE(2026,8,1))) -> 187046.19 | I8: =1*(SUMIFS('GL Extract'!$I$4:$I$943,'GL Extract'!$C$4:$C$943,"6000",'GL Extract'!$B$4:$B$943,">="&DATE(2026,8,1),'GL Extract'!$B$4:$B$943,"<"&DATE(2026,9,1))) -> 190383.35 | J8: =1*(SUMIFS('GL Extract'!$I$4:$I$943,'GL Extract'!$C$4:$C$943,"6000",'GL Extract'!$B$4:$B$943,">="&DATE(2026,9,1),'GL Extract'!$B$4:$B$943,"<"&DATE(2026,10,1))+SUMIF('Adjustment Journals'!$C$4:$C$17,"6000",'Adjustment Journals'!$H$4:$H$17)) -> 228218.54 | K8: =SUM(B8:J8) -> 1709430.3 | L8: =Budget!K6 -> 1666000 | M8: =K8-L8 -> 43430.304 | N8: =IFERROR(M8/L8,0) -> 0.02606861
A9: Employer Costs | B9: =1*(SUMIFS('GL Extract'!$I$4:$I$943,'GL Extract'!$C$4:$C$943,"6100",'GL Extract'!$B$4:$B$943,">="&DATE(2026,1,1),'GL Extract'!$B$4:$B$943,"<"&DATE(2026,2,1))) -> 24782.21 | C9: =1*(SUMIFS('GL Extract'!$I$4:$I$943,'GL Extract'!$C$4:$C$943,"6100",'GL Extract'!$B$4:$B$943,">="&DATE(2026,2,1),'GL Extract'!$B$4:$B$943,"<"&DATE(2026,3,1))) -> 24430.572 | D9: =1*(SUMIFS('GL Extract'!$I$4:$I$943,'GL Extract'!$C$4:$C$943,"6100",'GL Extract'!$B$4:$B$943,">="&DATE(2026,3,1),'GL Extract'!$B$4:$B$943,"<"&DATE(2026,4,1))) -> 24892.256 | E9: =1*(SUMIFS('GL Extract'!$I$4:$I$943,'GL Extract'!$C$4:$C$943,"6100",'GL Extract'!$B$4:$B$943,">="&DATE(2026,4,1),'GL Extract'!$B$4:$B$943,"<"&DATE(2026,5,1))) -> 24530.982 | F9: =1*(SUMIFS('GL Extract'!$I$4:$I$943,'GL Extract'!$C$4:$C$943,"6100",'GL Extract'!$B$4:$B$943,">="&DATE(2026,5,1),'GL Extract'!$B$4:$B$943,"<"&DATE(2026,6,1))) -> 25039.592 | G9: =1*(SUMIFS('GL Extract'!$I$4:$I$943,'GL Extract'!$C$4:$C$943,"6100",'GL Extract'!$B$4:$B$943,">="&DATE(2026,6,1),'GL Extract'!$B$4:$B$943,"<"&DATE(2026,7,1))) -> 25334.99 | H9: =1*(SUMIFS('GL Extract'!$I$4:$I$943,'GL Extract'!$C$4:$C$943,"6100",'GL Extract'!$B$4:$B$943,">="&DATE(2026,7,1),'GL Extract'!$B$4:$B$943,"<"&DATE(2026,8,1))) -> 25251.236 | I9: =1*(SUMIFS('GL Extract'!$I$4:$I$943,'GL Extract'!$C$4:$C$943,"6100",'GL Extract'!$B$4:$B$943,">="&DATE(2026,8,1),'GL Extract'!$B$4:$B$943,"<"&DATE(2026,9,1))) -> 25701.752 | J9: =1*(SUMIFS('GL Extract'!$I$4:$I$943,'GL Extract'!$C$4:$C$943,"6100",'GL Extract'!$B$4:$B$943,">="&DATE(2026,9,1),'GL Extract'!$B$4:$B$943,"<"&DATE(2026,10,1))+SUMIF('Adjustment Journals'!$C$4:$C$17,"6100",'Adjustment Journals'!$H$4:$H$17)) -> 26084.502 | K9: =SUM(B9:J9) -> 226048.09 | L9: =Budget!K7 -> 224910 | M9: =K9-L9 -> 1138.091 | N9: =IFERROR(M9/L9,0) -> 0.0050602064
A10: Marketing | B10: =1*(SUMIFS('GL Extract'!$I$4:$I$943,'GL Extract'!$C$4:$C$943,"6200",'GL Extract'!$B$4:$B$943,">="&DATE(2026,1,1),'GL Extract'!$B$4:$B$943,"<"&DATE(2026,2,1))) -> 60208.157 | C10: =1*(SUMIFS('GL Extract'!$I$4:$I$943,'GL Extract'!$C$4:$C$943,"6200",'GL Extract'!$B$4:$B$943,">="&DATE(2026,2,1),'GL Extract'!$B$4:$B$943,"<"&DATE(2026,3,1))) -> 65397.667 | D10: =1*(SUMIFS('GL Extract'!$I$4:$I$943,'GL Extract'!$C$4:$C$943,"6200",'GL Extract'!$B$4:$B$943,">="&DATE(2026,3,1),'GL Extract'!$B$4:$B$943,"<"&DATE(2026,4,1))) -> 61713.152 | E10: =1*(SUMIFS('GL Extract'!$I$4:$I$943,'GL Extract'!$C$4:$C$943,"6200",'GL Extract'!$B$4:$B$943,">="&DATE(2026,4,1),'GL Extract'!$B$4:$B$943,"<"&DATE(2026,5,1))) -> 70443.091 | F10: =1*(SUMIFS('GL Extract'!$I$4:$I$943,'GL Extract'!$C$4:$C$943,"6200",'GL Extract'!$B$4:$B$943,">="&DATE(2026,5,1),'GL Extract'!$B$4:$B$943,"<"&DATE(2026,6,1))) -> 67283.626 | G10: =1*(SUMIFS('GL Extract'!$I$4:$I$943,'GL Extract'!$C$4:$C$943,"6200",'GL Extract'!$B$4:$B$943,">="&DATE(2026,6,1),'GL Extract'!$B$4:$B$943,"<"&DATE(2026,7,1))) -> 74360.051 | H10: =1*(SUMIFS('GL Extract'!$I$4:$I$943,'GL Extract'!$C$4:$C$943,"6200",'GL Extract'!$B$4:$B$943,">="&DATE(2026,7,1),'GL Extract'!$B$4:$B$943,"<"&DATE(2026,8,1))) -> 70152.018 | I10: =1*(SUMIFS('GL Extract'!$I$4:$I$943,'GL Extract'!$C$4:$C$943,"6200",'GL Extract'!$B$4:$B$943,">="&DATE(2026,8,1),'GL Extract'!$B$4:$B$943,"<"&DATE(2026,9,1))) -> 76119.34 | J10: =1*(SUMIFS('GL Extract'!$I$4:$I$943,'GL Extract'!$C$4:$C$943,"6200",'GL Extract'!$B$4:$B$943,">="&DATE(2026,9,1),'GL Extract'!$B$4:$B$943,"<"&DATE(2026,10,1))+SUMIF('Adjustment Journals'!$C$4:$C$17,"6200",'Adjustment Journals'!$H$4:$H$17)) -> 102743.53 | K10: =SUM(B10:J10) -> 648420.63 | L10: =Budget!K8 -> 619200 | M10: =K10-L10 -> 29220.634 | N10: =IFERROR(M10/L10,0) -> 0.047190947
A11: Rent | B11: =1*(SUMIFS('GL Extract'!$I$4:$I$943,'GL Extract'!$C$4:$C$943,"6300",'GL Extract'!$B$4:$B$943,">="&DATE(2026,1,1),'GL Extract'!$B$4:$B$943,"<"&DATE(2026,2,1))) -> 52000 | C11: =1*(SUMIFS('GL Extract'!$I$4:$I$943,'GL Extract'!$C$4:$C$943,"6300",'GL Extract'!$B$4:$B$943,">="&DATE(2026,2,1),'GL Extract'!$B$4:$B$943,"<"&DATE(2026,3,1))) -> 52000 | D11: =1*(SUMIFS('GL Extract'!$I$4:$I$943,'GL Extract'!$C$4:$C$943,"6300",'GL Extract'!$B$4:$B$943,">="&DATE(2026,3,1),'GL Extract'!$B$4:$B$943,"<"&DATE(2026,4,1))) -> 52000 | E11: =1*(SUMIFS('GL Extract'!$I$4:$I$943,'GL Extract'!$C$4:$C$943,"6300",'GL Extract'!$B$4:$B$943,">="&DATE(2026,4,1),'GL Extract'!$B$4:$B$943,"<"&DATE(2026,5,1))) -> 52000 | F11: =1*(SUMIFS('GL Extract'!$I$4:$I$943,'GL Extract'!$C$4:$C$943,"6300",'GL Extract'!$B$4:$B$943,">="&DATE(2026,5,1),'GL Extract'!$B$4:$B$943,"<"&DATE(2026,6,1))) -> 52000 | G11: =1*(SUMIFS('GL Extract'!$I$4:$I$943,'GL Extract'!$C$4:$C$943,"6300",'GL Extract'!$B$4:$B$943,">="&DATE(2026,6,1),'GL Extract'!$B$4:$B$943,"<"&DATE(2026,7,1))) -> 52000 | H11: =1*(SUMIFS('GL Extract'!$I$4:$I$943,'GL Extract'!$C$4:$C$943,"6300",'GL Extract'!$B$4:$B$943,">="&DATE(2026,7,1),'GL Extract'!$B$4:$B$943,"<"&DATE(2026,8,1))) -> 52000 | I11: =1*(SUMIFS('GL Extract'!$I$4:$I$943,'GL Extract'!$C$4:$C$943,"6300",'GL Extract'!$B$4:$B$943,">="&DATE(2026,8,1),'GL Extract'!$B$4:$B$943,"<"&DATE(2026,9,1))) -> 52000 | J11: =1*(SUMIFS('GL Extract'!$I$4:$I$943,'GL Extract'!$C$4:$C$943,"6300",'GL Extract'!$B$4:$B$943,">="&DATE(2026,9,1),'GL Extract'!$B$4:$B$943,"<"&DATE(2026,10,1))+SUMIF('Adjustment Journals'!$C$4:$C$17,"6300",'Adjustment Journals'!$H$4:$H$17)) -> 52000 | K11: =SUM(B11:J11) -> 468000 | L11: =Budget!K9 -> 468000 | M11: =K11-L11 -> 0 | N11: =IFERROR(M11/L11,0) -> 0
A12: Utilities | B12: =1*(SUMIFS('GL Extract'!$I$4:$I$943,'GL Extract'!$C$4:$C$943,"6400",'GL Extract'!$B$4:$B$943,">="&DATE(2026,1,1),'GL Extract'!$B$4:$B$943,"<"&DATE(2026,2,1))) -> 19822.433 | C12: =1*(SUMIFS('GL Extract'!$I$4:$I$943,'GL Extract'!$C$4:$C$943,"6400",'GL Extract'!$B$4:$B$943,">="&DATE(2026,2,1),'GL Extract'!$B$4:$B$943,"<"&DATE(2026,3,1))) -> 20248.498 | D12: =1*(SUMIFS('GL Extract'!$I$4:$I$943,'GL Extract'!$C$4:$C$943,"6400",'GL Extract'!$B$4:$B$943,">="&DATE(2026,3,1),'GL Extract'!$B$4:$B$943,"<"&DATE(2026,4,1))) -> 20775.912 | E12: =1*(SUMIFS('GL Extract'!$I$4:$I$943,'GL Extract'!$C$4:$C$943,"6400",'GL Extract'!$B$4:$B$943,">="&DATE(2026,4,1),'GL Extract'!$B$4:$B$943,"<"&DATE(2026,5,1))) -> 19940.763 | F12: =1*(SUMIFS('GL Extract'!$I$4:$I$943,'GL Extract'!$C$4:$C$943,"6400",'GL Extract'!$B$4:$B$943,">="&DATE(2026,5,1),'GL Extract'!$B$4:$B$943,"<"&DATE(2026,6,1))) -> 21051.681 | G12: =1*(SUMIFS('GL Extract'!$I$4:$I$943,'GL Extract'!$C$4:$C$943,"6400",'GL Extract'!$B$4:$B$943,">="&DATE(2026,6,1),'GL Extract'!$B$4:$B$943,"<"&DATE(2026,7,1))) -> 21369.877 | H12: =1*(SUMIFS('GL Extract'!$I$4:$I$943,'GL Extract'!$C$4:$C$943,"6400",'GL Extract'!$B$4:$B$943,">="&DATE(2026,7,1),'GL Extract'!$B$4:$B$943,"<"&DATE(2026,8,1))) -> 20812.954 | I12: =1*(SUMIFS('GL Extract'!$I$4:$I$943,'GL Extract'!$C$4:$C$943,"6400",'GL Extract'!$B$4:$B$943,">="&DATE(2026,8,1),'GL Extract'!$B$4:$B$943,"<"&DATE(2026,9,1))) -> 21739.113 | J12: =1*(SUMIFS('GL Extract'!$I$4:$I$943,'GL Extract'!$C$4:$C$943,"6400",'GL Extract'!$B$4:$B$943,">="&DATE(2026,9,1),'GL Extract'!$B$4:$B$943,"<"&DATE(2026,10,1))+SUMIF('Adjustment Journals'!$C$4:$C$17,"6400",'Adjustment Journals'!$H$4:$H$17)) -> 22000 | K12: =SUM(B12:J12) -> 187761.23 | L12: =Budget!K10 -> 190800 | M12: =K12-L12 -> -3038.7693 | N12: =IFERROR(M12/L12,0) -> -0.015926464
A13: Professional Fees | B13: =1*(SUMIFS('GL Extract'!$I$4:$I$943,'GL Extract'!$C$4:$C$943,"6500",'GL Extract'!$B$4:$B$943,">="&DATE(2026,1,1),'GL Extract'!$B$4:$B$943,"<"&DATE(2026,2,1))) -> 14134.749 | C13: =1*(SUMIFS('GL Extract'!$I$4:$I$943,'GL Extract'!$C$4:$C$943,"6500",'GL Extract'!$B$4:$B$943,">="&DATE(2026,2,1),'GL Extract'!$B$4:$B$943,"<"&DATE(2026,3,1))) -> 14572.913 | D13: =1*(SUMIFS('GL Extract'!$I$4:$I$943,'GL Extract'!$C$4:$C$943,"6500",'GL Extract'!$B$4:$B$943,">="&DATE(2026,3,1),'GL Extract'!$B$4:$B$943,"<"&DATE(2026,4,1))) -> 14928.638 | E13: =1*(SUMIFS('GL Extract'!$I$4:$I$943,'GL Extract'!$C$4:$C$943,"6500",'GL Extract'!$B$4:$B$943,">="&DATE(2026,4,1),'GL Extract'!$B$4:$B$943,"<"&DATE(2026,5,1))) -> 14077.717 | F13: =1*(SUMIFS('GL Extract'!$I$4:$I$943,'GL Extract'!$C$4:$C$943,"6500",'GL Extract'!$B$4:$B$943,">="&DATE(2026,5,1),'GL Extract'!$B$4:$B$943,"<"&DATE(2026,6,1))) -> 14690.145 | G13: =1*(SUMIFS('GL Extract'!$I$4:$I$943,'GL Extract'!$C$4:$C$943,"6500",'GL Extract'!$B$4:$B$943,">="&DATE(2026,6,1),'GL Extract'!$B$4:$B$943,"<"&DATE(2026,7,1))) -> 16639.717 | H13: =1*(SUMIFS('GL Extract'!$I$4:$I$943,'GL Extract'!$C$4:$C$943,"6500",'GL Extract'!$B$4:$B$943,">="&DATE(2026,7,1),'GL Extract'!$B$4:$B$943,"<"&DATE(2026,8,1))) -> 16742.389 | I13: =1*(SUMIFS('GL Extract'!$I$4:$I$943,'GL Extract'!$C$4:$C$943,"6500",'GL Extract'!$B$4:$B$943,">="&DATE(2026,8,1),'GL Extract'!$B$4:$B$943,"<"&DATE(2026,9,1))) -> 16573.924 | J13: =1*(SUMIFS('GL Extract'!$I$4:$I$943,'GL Extract'!$C$4:$C$943,"6500",'GL Extract'!$B$4:$B$943,">="&DATE(2026,9,1),'GL Extract'!$B$4:$B$943,"<"&DATE(2026,10,1))+SUMIF('Adjustment Journals'!$C$4:$C$17,"6500",'Adjustment Journals'!$H$4:$H$17)) -> 18000 | K13: =SUM(B13:J13) -> 140360.19 | L13: =Budget!K11 -> 146700 | M13: =K13-L13 -> -6339.8076 | N13: =IFERROR(M13/L13,0) -> -0.043216139
A14: Insurance | B14: =1*(SUMIFS('GL Extract'!$I$4:$I$943,'GL Extract'!$C$4:$C$943,"6550",'GL Extract'!$B$4:$B$943,">="&DATE(2026,1,1),'GL Extract'!$B$4:$B$943,"<"&DATE(2026,2,1))) -> 96000 | C14: =1*(SUMIFS('GL Extract'!$I$4:$I$943,'GL Extract'!$C$4:$C$943,"6550",'GL Extract'!$B$4:$B$943,">="&DATE(2026,2,1),'GL Extract'!$B$4:$B$943,"<"&DATE(2026,3,1))) -> 0 | D14: =1*(SUMIFS('GL Extract'!$I$4:$I$943,'GL Extract'!$C$4:$C$943,"6550",'GL Extract'!$B$4:$B$943,">="&DATE(2026,3,1),'GL Extract'!$B$4:$B$943,"<"&DATE(2026,4,1))) -> 0 | E14: =1*(SUMIFS('GL Extract'!$I$4:$I$943,'GL Extract'!$C$4:$C$943,"6550",'GL Extract'!$B$4:$B$943,">="&DATE(2026,4,1),'GL Extract'!$B$4:$B$943,"<"&DATE(2026,5,1))) -> 0 | F14: =1*(SUMIFS('GL Extract'!$I$4:$I$943,'GL Extract'!$C$4:$C$943,"6550",'GL Extract'!$B$4:$B$943,">="&DATE(2026,5,1),'GL Extract'!$B$4:$B$943,"<"&DATE(2026,6,1))) -> 0 | G14: =1*(SUMIFS('GL Extract'!$I$4:$I$943,'GL Extract'!$C$4:$C$943,"6550",'GL Extract'!$B$4:$B$943,">="&DATE(2026,6,1),'GL Extract'!$B$4:$B$943,"<"&DATE(2026,7,1))) -> 0 | H14: =1*(SUMIFS('GL Extract'!$I$4:$I$943,'GL Extract'!$C$4:$C$943,"6550",'GL Extract'!$B$4:$B$943,">="&DATE(2026,7,1),'GL Extract'!$B$4:$B$943,"<"&DATE(2026,8,1))) -> 0 | I14: =1*(SUMIFS('GL Extract'!$I$4:$I$943,'GL Extract'!$C$4:$C$943,"6550",'GL Extract'!$B$4:$B$943,">="&DATE(2026,8,1),'GL Extract'!$B$4:$B$943,"<"&DATE(2026,9,1))) -> 0 | J14: =1*(SUMIFS('GL Extract'!$I$4:$I$943,'GL Extract'!$C$4:$C$943,"6550",'GL Extract'!$B$4:$B$943,">="&DATE(2026,9,1),'GL Extract'!$B$4:$B$943,"<"&DATE(2026,10,1))+SUMIF('Adjustment Journals'!$C$4:$C$17,"6550",'Adjustment Journals'!$H$4:$H$17)) -> -24000 | K14: =SUM(B14:J14) -> 72000 | L14: =Budget!K12 -> 72000 | M14: =K14-L14 -> 0 | N14: =IFERROR(M14/L14,0) -> 0
A15: Software & IT | B15: =1*(SUMIFS('GL Extract'!$I$4:$I$943,'GL Extract'!$C$4:$C$943,"6600",'GL Extract'!$B$4:$B$943,">="&DATE(2026,1,1),'GL Extract'!$B$4:$B$943,"<"&DATE(2026,2,1))) -> 23800 | C15: =1*(SUMIFS('GL Extract'!$I$4:$I$943,'GL Extract'!$C$4:$C$943,"6600",'GL Extract'!$B$4:$B$943,">="&DATE(2026,2,1),'GL Extract'!$B$4:$B$943,"<"&DATE(2026,3,1))) -> 25600 | D15: =1*(SUMIFS('GL Extract'!$I$4:$I$943,'GL Extract'!$C$4:$C$943,"6600",'GL Extract'!$B$4:$B$943,">="&DATE(2026,3,1),'GL Extract'!$B$4:$B$943,"<"&DATE(2026,4,1))) -> 22000 | E15: =1*(SUMIFS('GL Extract'!$I$4:$I$943,'GL Extract'!$C$4:$C$943,"6600",'GL Extract'!$B$4:$B$943,">="&DATE(2026,4,1),'GL Extract'!$B$4:$B$943,"<"&DATE(2026,5,1))) -> 23800 | F15: =1*(SUMIFS('GL Extract'!$I$4:$I$943,'GL Extract'!$C$4:$C$943,"6600",'GL Extract'!$B$4:$B$943,">="&DATE(2026,5,1),'GL Extract'!$B$4:$B$943,"<"&DATE(2026,6,1))) -> 25600 | G15: =1*(SUMIFS('GL Extract'!$I$4:$I$943,'GL Extract'!$C$4:$C$943,"6600",'GL Extract'!$B$4:$B$943,">="&DATE(2026,6,1),'GL Extract'!$B$4:$B$943,"<"&DATE(2026,7,1))) -> 22000 | H15: =1*(SUMIFS('GL Extract'!$I$4:$I$943,'GL Extract'!$C$4:$C$943,"6600",'GL Extract'!$B$4:$B$943,">="&DATE(2026,7,1),'GL Extract'!$B$4:$B$943,"<"&DATE(2026,8,1))) -> 23800 | I15: =1*(SUMIFS('GL Extract'!$I$4:$I$943,'GL Extract'!$C$4:$C$943,"6600",'GL Extract'!$B$4:$B$943,">="&DATE(2026,8,1),'GL Extract'!$B$4:$B$943,"<"&DATE(2026,9,1))) -> 25600 | J15: =1*(SUMIFS('GL Extract'!$I$4:$I$943,'GL Extract'!$C$4:$C$943,"6600",'GL Extract'!$B$4:$B$943,">="&DATE(2026,9,1),'GL Extract'!$B$4:$B$943,"<"&DATE(2026,10,1))+SUMIF('Adjustment Journals'!$C$4:$C$17,"6600",'Adjustment Journals'!$H$4:$H$17)) -> 22000 | K15: =SUM(B15:J15) -> 214200 | L15: =Budget!K13 -> 207000 | M15: =K15-L15 -> 7200 | N15: =IFERROR(M15/L15,0) -> 0.034782609
A16: Travel | B16: =1*(SUMIFS('GL Extract'!$I$4:$I$943,'GL Extract'!$C$4:$C$943,"6700",'GL Extract'!$B$4:$B$943,">="&DATE(2026,1,1),'GL Extract'!$B$4:$B$943,"<"&DATE(2026,2,1))) -> 7868.4976 | C16: =1*(SUMIFS('GL Extract'!$I$4:$I$943,'GL Extract'!$C$4:$C$943,"6700",'GL Extract'!$B$4:$B$943,">="&DATE(2026,2,1),'GL Extract'!$B$4:$B$943,"<"&DATE(2026,3,1))) -> 8621.2821 | D16: =1*(SUMIFS('GL Extract'!$I$4:$I$943,'GL Extract'!$C$4:$C$943,"6700",'GL Extract'!$B$4:$B$943,">="&DATE(2026,3,1),'GL Extract'!$B$4:$B$943,"<"&DATE(2026,4,1))) -> 8736.824 | E16: =1*(SUMIFS('GL Extract'!$I$4:$I$943,'GL Extract'!$C$4:$C$943,"6700",'GL Extract'!$B$4:$B$943,">="&DATE(2026,4,1),'GL Extract'!$B$4:$B$943,"<"&DATE(2026,5,1))) -> 7590.5358 | F16: =1*(SUMIFS('GL Extract'!$I$4:$I$943,'GL Extract'!$C$4:$C$943,"6700",'GL Extract'!$B$4:$B$943,">="&DATE(2026,5,1),'GL Extract'!$B$4:$B$943,"<"&DATE(2026,6,1))) -> 8709.5964 | G16: =1*(SUMIFS('GL Extract'!$I$4:$I$943,'GL Extract'!$C$4:$C$943,"6700",'GL Extract'!$B$4:$B$943,">="&DATE(2026,6,1),'GL Extract'!$B$4:$B$943,"<"&DATE(2026,7,1))) -> 10261.467 | H16: =1*(SUMIFS('GL Extract'!$I$4:$I$943,'GL Extract'!$C$4:$C$943,"6700",'GL Extract'!$B$4:$B$943,">="&DATE(2026,7,1),'GL Extract'!$B$4:$B$943,"<"&DATE(2026,8,1))) -> 8260.8632 | I16: =1*(SUMIFS('GL Extract'!$I$4:$I$943,'GL Extract'!$C$4:$C$943,"6700",'GL Extract'!$B$4:$B$943,">="&DATE(2026,8,1),'GL Extract'!$B$4:$B$943,"<"&DATE(2026,9,1))) -> 11150.296 | J16: =1*(SUMIFS('GL Extract'!$I$4:$I$943,'GL Extract'!$C$4:$C$943,"6700",'GL Extract'!$B$4:$B$943,">="&DATE(2026,9,1),'GL Extract'!$B$4:$B$943,"<"&DATE(2026,10,1))+SUMIF('Adjustment Journals'!$C$4:$C$17,"6700",'Adjustment Journals'!$H$4:$H$17)) -> 11555.123 | K16: =SUM(B16:J16) -> 82754.485 | L16: =Budget!K14 -> 81000 | M16: =K16-L16 -> 1754.4847 | N16: =IFERROR(M16/L16,0) -> 0.021660305
A17: Total Opex pre-D&A | B17: =SUM(B8:B16) -> 482187.97 | C17: =SUM(C8:C16) -> 391838.13 | D17: =SUM(D8:D16) -> 389433.86 | E17: =SUM(E8:E16) -> 394094.07 | F17: =SUM(F8:F16) -> 399853.1 | G17: =SUM(G8:G16) -> 409632.69 | H17: =SUM(H8:H16) -> 404065.65 | I17: =SUM(I8:I16) -> 419267.77 | J17: =SUM(J8:J16) -> 458601.69 | K17: =SUM(B17:J17) -> 3748974.9 | L17: =SUM(L8:L16) -> 3675610 | M17: =K17-L17 -> 73364.937 | N17: =IFERROR(M17/L17,0) -> 0.019959935
A18: EBITDA | B18: =B6-B17 -> -117287.97 | C18: =C6-C17 -> -14123.132 | D18: =D6-D17 -> 2566.1378 | E18: =E6-E17 -> 10905.935 | F18: =F6-F17 -> 20506.903 | G18: =G6-G17 -> 21072.307 | H18: =H6-H17 -> 35344.347 | I18: =I6-I17 -> 30192.228 | J18: =J6-J17 -> 3223.3062 | K18: =SUM(B18:J18) -> -7599.9369 | L18: =L6-L17 -> 27890 | M18: =K18-L18 -> -35489.937 | N18: =IFERROR(M18/L18,0) -> -1.2724968
A19: EBITDA Margin % | B19: =IFERROR(B18/B4,0) -> -0.14303411 | C19: =IFERROR(C18/C4,0) -> -0.016713766 | D19: =IFERROR(D18/D4,0) -> 0.0029327289 | E19: =IFERROR(E18/E4,0) -> 0.012117705 | F19: =IFERROR(F18/F4,0) -> 0.022050433 | G19: =IFERROR(G18/G4,0) -> 0.022065243 | H19: =IFERROR(H18/H4,0) -> 0.036437471 | I19: =IFERROR(I18/I4,0) -> 0.0304972 | ... L19: =IFERROR(L18/L4,0) -> 0.0033888214 | M19: =K19-L19 -> -0.0043044764 | N19: -
A20: Depreciation | B20: =1*(SUMIFS('GL Extract'!$I$4:$I$943,'GL Extract'!$C$4:$C$943,"6800",'GL Extract'!$B$4:$B$943,">="&DATE(2026,1,1),'GL Extract'!$B$4:$B$943,"<"&DATE(2026,2,1))) -> 15000 | C20: =1*(SUMIFS('GL Extract'!$I$4:$I$943,'GL Extract'!$C$4:$C$943,"6800",'GL Extract'!$B$4:$B$943,">="&DATE(2026,2,1),'GL Extract'!$B$4:$B$943,"<"&DATE(2026,3,1))) -> 15000 | D20: =1*(SUMIFS('GL Extract'!$I$4:$I$943,'GL Extract'!$C$4:$C$943,"6800",'GL Extract'!$B$4:$B$943,">="&DATE(2026,3,1),'GL Extract'!$B$4:$B$943,"<"&DATE(2026,4,1))) -> 15000 | E20: =1*(SUMIFS('GL Extract'!$I$4:$I$943,'GL Extract'!$C$4:$C$943,"6800",'GL Extract'!$B$4:$B$943,">="&DATE(2026,4,1),'GL Extract'!$B$4:$B$943,"<"&DATE(2026,5,1))) -> 15000 | F20: =1*(SUMIFS('GL Extract'!$I$4:$I$943,'GL Extract'!$C$4:$C$943,"6800",'GL Extract'!$B$4:$B$943,">="&DATE(2026,5,1),'GL Extract'!$B$4:$B$943,"<"&DATE(2026,6,1))) -> 15000 | G20: =1*(SUMIFS('GL Extract'!$I$4:$I$943,'GL Extract'!$C$4:$C$943,"6800",'GL Extract'!$B$4:$B$943,">="&DATE(2026,6,1),'GL Extract'!$B$4:$B$943,"<"&DATE(2026,7,1))) -> 15000 | H20: =1*(SUMIFS('GL Extract'!$I$4:$I$943,'GL Extract'!$C$4:$C$943,"6800",'GL Extract'!$B$4:$B$943,">="&DATE(2026,7,1),'GL Extract'!$B$4:$B$943,"<"&DATE(2026,8,1))) -> 15000 | I20: =1*(SUMIFS('GL Extract'!$I$4:$I$943,'GL Extract'!$C$4:$C$943,"6800",'GL Extract'!$B$4:$B$943,">="&DATE(2026,8,1),'GL Extract'!$B$4:$B$943,"<"&DATE(2026,9,1))) -> 15000 | J20: =1*(SUMIFS('GL Extract'!$I$4:$I$943,'GL Extract'!$C$4:$C$943,"6800",'GL Extract'!$B$4:$B$943,">="&DATE(2026,9,1),'GL Extract'!$B$4:$B$943,"<"&DATE(2026,10,1))+SUMIF('Adjustment Journals'!$C$4:$C$17,"6800",'Adjustment Journals'!$H$4:$H$17)) -> 15000 | K20: =SUM(B20:J20) -> 135000 | L20: =Budget!K15 -> 135000 | M20: =K20-L20 -> 0 | N20: =IFERROR(M20/L20,0) -> 0
A21: Bad Debt | B21: =1*(SUMIFS('GL Extract'!$I$4:$I$943,'GL Extract'!$C$4:$C$943,"6900",'GL Extract'!$B$4:$B$943,">="&DATE(2026,1,1),'GL Extract'!$B$4:$B$943,"<"&DATE(2026,2,1))) -> 0 | C21: =1*(SUMIFS('GL Extract'!$I$4:$I$943,'GL Extract'!$C$4:$C$943,"6900",'GL Extract'!$B$4:$B$943,">="&DATE(2026,2,1),'GL Extract'!$B$4:$B$943,"<"&DATE(2026,3,1))) -> 0 | D21: =1*(SUMIFS('GL Extract'!$I$4:$I$943,'GL Extract'!$C$4:$C$943,"6900",'GL Extract'!$B$4:$B$943,">="&DATE(2026,3,1),'GL Extract'!$B$4:$B$943,"<"&DATE(2026,4,1))) -> 0 | E21: =1*(SUMIFS('GL Extract'!$I$4:$I$943,'GL Extract'!$C$4:$C$943,"6900",'GL Extract'!$B$4:$B$943,">="&DATE(2026,4,1),'GL Extract'!$B$4:$B$943,"<"&DATE(2026,5,1))) -> 0 | F21: =1*(SUMIFS('GL Extract'!$I$4:$I$943,'GL Extract'!$C$4:$C$943,"6900",'GL Extract'!$B$4:$B$943,">="&DATE(2026,5,1),'GL Extract'!$B$4:$B$943,"<"&DATE(2026,6,1))) -> 0 | G21: =1*(SUMIFS('GL Extract'!$I$4:$I$943,'GL Extract'!$C$4:$C$943,"6900",'GL Extract'!$B$4:$B$943,">="&DATE(2026,6,1),'GL Extract'!$B$4:$B$943,"<"&DATE(2026,7,1))) -> 0 | H21: =1*(SUMIFS('GL Extract'!$I$4:$I$943,'GL Extract'!$C$4:$C$943,"6900",'GL Extract'!$B$4:$B$943,">="&DATE(2026,7,1),'GL Extract'!$B$4:$B$943,"<"&DATE(2026,8,1))) -> 0 | I21: =1*(SUMIFS('GL Extract'!$I$4:$I$943,'GL Extract'!$C$4:$C$943,"6900",'GL Extract'!$B$4:$B$943,">="&DATE(2026,8,1),'GL Extract'!$B$4:$B$943,"<"&DATE(2026,9,1))) -> 0 | J21: =1*(SUMIFS('GL Extract'!$I$4:$I$943,'GL Extract'!$C$4:$C$943,"6900",'GL Extract'!$B$4:$B$943,">="&DATE(2026,9,1),'GL Extract'!$B$4:$B$943,"<"&DATE(2026,10,1))+SUMIF('Adjustment Journals'!$C$4:$C$17,"6900",'Adjustment Journals'!$H$4:$H$17)) -> 5000 | K21: =SUM(B21:J21) -> 5000 | L21: =Budget!K16 -> 27000 | M21: =K21-L21 -> -22000 | N21: =IFERROR(M21/L21,0) -> -0.81481481
A22: Operating Profit | B22: =B18-B20-B21 -> -132287.97 | C22: =C18-C20-C21 -> -29123.132 | D22: =D18-D20-D21 -> -12433.862 | E22: =E18-E20-E21 -> -4094.0653 | F22: =F18-F20-F21 -> 5506.9031 | G22: =G18-G20-G21 -> 6072.3068 | H22: =H18-H20-H21 -> 20344.347 | I22: =I18-I20-I21 -> 15192.228 | J22: =J18-J20-J21 -> -16776.694 | K22: =SUM(B22:J22) -> -147599.94 | L22: =L18-L20-L21 -> -134110 | M22: =K22-L22 -> -13489.937 | N22: =IFERROR(M22/L22,0) -> 0.1005886
A23: Interest | B23: =1*(SUMIFS('GL Extract'!$I$4:$I$943,'GL Extract'!$C$4:$C$943,"7000",'GL Extract'!$B$4:$B$943,">="&DATE(2026,1,1),'GL Extract'!$B$4:$B$943,"<"&DATE(2026,2,1))) -> 5500 | C23: =1*(SUMIFS('GL Extract'!$I$4:$I$943,'GL Extract'!$C$4:$C$943,"7000",'GL Extract'!$B$4:$B$943,">="&DATE(2026,2,1),'GL Extract'!$B$4:$B$943,"<"&DATE(2026,3,1))) -> 5500 | D23: =1*(SUMIFS('GL Extract'!$I$4:$I$943,'GL Extract'!$C$4:$C$943,"7000",'GL Extract'!$B$4:$B$943,">="&DATE(2026,3,1),'GL Extract'!$B$4:$B$943,"<"&DATE(2026,4,1))) -> 5500 | E23: =1*(SUMIFS('GL Extract'!$I$4:$I$943,'GL Extract'!$C$4:$C$943,"7000",'GL Extract'!$B$4:$B$943,">="&DATE(2026,4,1),'GL Extract'!$B$4:$B$943,"<"&DATE(2026,5,1))) -> 5500 | F23: =1*(SUMIFS('GL Extract'!$I$4:$I$943,'GL Extract'!$C$4:$C$943,"7000",'GL Extract'!$B$4:$B$943,">="&DATE(2026,5,1),'GL Extract'!$B$4:$B$943,"<"&DATE(2026,6,1))) -> 5500 | G23: =1*(SUMIFS('GL Extract'!$I$4:$I$943,'GL Extract'!$C$4:$C$943,"7000",'GL Extract'!$B$4:$B$943,">="&DATE(2026,6,1),'GL Extract'!$B$4:$B$943,"<"&DATE(2026,7,1))) -> 5500 | H23: =1*(SUMIFS('GL Extract'!$I$4:$I$943,'GL Extract'!$C$4:$C$943,"7000",'GL Extract'!$B$4:$B$943,">="&DATE(2026,7,1),'GL Extract'!$B$4:$B$943,"<"&DATE(2026,8,1))) -> 5500 | I23: =1*(SUMIFS('GL Extract'!$I$4:$I$943,'GL Extract'!$C$4:$C$943,"7000",'GL Extract'!$B$4:$B$943,">="&DATE(2026,8,1),'GL Extract'!$B$4:$B$943,"<"&DATE(2026,9,1))) -> 5500 | J23: =1*(SUMIFS('GL Extract'!$I$4:$I$943,'GL Extract'!$C$4:$C$943,"7000",'GL Extract'!$B$4:$B$943,">="&DATE(2026,9,1),'GL Extract'!$B$4:$B$943,"<"&DATE(2026,10,1))+SUMIF('Adjustment Journals'!$C$4:$C$17,"7000",'Adjustment Journals'!$H$4:$H$17)) -> 5500 | K23: =SUM(B23:J23) -> 49500 | L23: =Budget!K17 -> 49500 | M23: =K23-L23 -> 0 | N23: =IFERROR(M23/L23,0) -> 0
A24: Profit Before Tax | B24: =B22-B23 -> -137787.97 | C24: =C22-C23 -> -34623.132 | D24: =D22-D23 -> -17933.862 | E24: =E22-E23 -> -9594.0653 | F24: =F22-F23 -> 6.9030805 | G24: =G22-G23 -> 572.30678 | H24: =H22-H23 -> 14844.347 | I24: =I22-I23 -> 9692.2284 | J24: =J22-J23 -> -22276.694 | K24: =SUM(B24:J24) -> -197099.94 | L24: =L22-L23 -> -183610 | M24: =K24-L24 -> -13489.937 | N24: =IFERROR(M24/L24,0) -> 0.0734706

Sheet Balance Sheet
A1: Balance Sheet — 30 Sep 2026
A3: Balance Sheet Line | B3: Opening (£) | C3: Sep Closing (£) | D3: Movement (£)
A4: Cash | B4: =1*SUMIF('Opening TB'!$A$4:$A$30,"1000",'Opening TB'!$C$4:$C$30) -> 450000 | C4: =1*SUMIF('Adjusted TB'!$A$4:$A$30,"1000",'Adjusted TB'!$H$4:$H$30) -> 857522.22 | D4: =C4-B4 -> 407522.22
A5: Trade Receivables | B5: =1*SUMIF('Opening TB'!$A$4:$A$30,"1100",'Opening TB'!$C$4:$C$30) -> 800000 | C5: =1*SUMIF('Adjusted TB'!$A$4:$A$30,"1100",'Adjusted TB'!$H$4:$H$30) -> 1151225 | D5: =C5-B5 -> 351225
A6: Allowance for Doubtful Debts | B6: =-1*SUMIF('Opening TB'!$A$4:$A$30,"1150",'Opening TB'!$C$4:$C$30) -> 30000 | C6: =-1*SUMIF('Adjusted TB'!$A$4:$A$30,"1150",'Adjusted TB'!$H$4:$H$30) -> 35000 | D6: =C6-B6 -> 5000
A7: Inventory | B7: =1*SUMIF('Opening TB'!$A$4:$A$30,"1200",'Opening TB'!$C$4:$C$30) -> 650000 | C7: =1*SUMIF('Adjusted TB'!$A$4:$A$30,"1200",'Adjusted TB'!$H$4:$H$30) -> 660084.8 | D7: =C7-B7 -> 10084.8
A8: Prepayments | B8: =1*SUMIF('Opening TB'!$A$4:$A$30,"1300",'Opening TB'!$C$4:$C$30) -> 90000 | C8: =1*SUMIF('Adjusted TB'!$A$4:$A$30,"1300",'Adjusted TB'!$H$4:$H$30) -> 114000 | D8: =C8-B8 -> 24000
A9: Property, Plant & Equipment | B9: =1*SUMIF('Opening TB'!$A$4:$A$30,"1400",'Opening TB'!$C$4:$C$30) -> 1200000 | C9: =1*SUMIF('Adjusted TB'!$A$4:$A$30,"1400",'Adjusted TB'!$H$4:$H$30) -> 1430000 | D9: =C9-B9 -> 230000
A10: Accumulated Depreciation | B10: =-1*SUMIF('Opening TB'!$A$4:$A$30,"1450",'Opening TB'!$C$4:$C$30) -> 350000 | C10: =-1*SUMIF('Adjusted TB'!$A$4:$A$30,"1450",'Adjusted TB'!$H$4:$H$30) -> 485000 | D10: =C10-B10 -> 135000
A11: Trade Payables | B11: =-1*SUMIF('Opening TB'!$A$4:$A$30,"2000",'Opening TB'!$C$4:$C$30) -> 600000 | C11: =-1*SUMIF('Adjusted TB'!$A$4:$A$30,"2000",'Adjusted TB'!$H$4:$H$30) -> 1639932 | D11: =C11-B11 -> 1039932
A12: Accrued Expenses | B12: =-1*SUMIF('Opening TB'!$A$4:$A$30,"2100",'Opening TB'!$C$4:$C$30) -> 150000 | C12: =-1*SUMIF('Adjusted TB'!$A$4:$A$30,"2100",'Adjusted TB'!$H$4:$H$30) -> 255000 | D12: =C12-B12 -> 105000
A13: Payroll Liabilities | B13: =-1*SUMIF('Opening TB'!$A$4:$A$30,"2200",'Opening TB'!$C$4:$C$30) -> 60000 | C13: =-1*SUMIF('Adjusted TB'!$A$4:$A$30,"2200",'Adjusted TB'!$H$4:$H$30) -> 60000 | D13: =C13-B13 -> 0
A14: Tax Payable | B14: =-1*SUMIF('Opening TB'!$A$4:$A$30,"2300",'Opening TB'!$C$4:$C$30) -> 100000 | C14: =-1*SUMIF('Adjusted TB'!$A$4:$A$30,"2300",'Adjusted TB'!$H$4:$H$30) -> 35000 | D14: =C14-B14 -> -65000
A15: Share Capital | B15: =-1*SUMIF('Opening TB'!$A$4:$A$30,"3000",'Opening TB'!$C$4:$C$30) -> 500000 | C15: =-1*SUMIF('Adjusted TB'!$A$4:$A$30,"3000",'Adjusted TB'!$H$4:$H$30) -> 500000 | D15: =C15-B15 -> 0
A16: Retained Earnings | B16: =-1*SUMIF('Opening TB'!$A$4:$A$30,"3100",'Opening TB'!$C$4:$C$30) -> 1400000 | C16: =-1*SUMIF('Adjusted TB'!$A$4:$A$30,"3100",'Adjusted TB'!$H$4:$H$30) -> 1400000 | D16: =C16-B16 -> 0
A19: Balance Sheet Summary
A20: Metric | B20: Sep Closing (£)
A21: Total Current Assets | B21: =C4+C5-C6+C7+C8 -> 2747832
A22: Net PP&E | B22: =C9-C10 -> 945000
A23: Total Assets | B23: =B21+B22 -> 3692832
A24: Total Current Liabilities | B24: =SUM(C11:C14) -> 1989932
A25: Total Equity incl. YTD PBT | B25: =SUM(C15:C16)+'Management P&L'!K24 -> 1702900.1
A26: Liabilities + Equity | B26: =B24+B25 -> 3692832
A27: Balance Check | B27: =B23-B26 -> 0

Sheet Bank Reconciliation
A1: Bank Reconciliation — 30 Sep 2026
A3: Outstanding reconciling items
A4: Item | B4: Type | C4: Amount (£) | D4: Source
A5: Deposit in transit 1 | B5: Outstanding deposit | C5: 8500 | D5: Synthetic bank reconciliation
A6: Deposit in transit 2 | B6: Outstanding deposit | C6: 7200 | D6: Synthetic bank reconciliation
A7: Deposit in transit 3 | B7: Outstanding deposit | C7: 6300 | D7: Synthetic bank reconciliation
A8: Unpresented payments | B8: Payment schedule | C8: 17000 | D8: Synthetic bank reconciliation
A11: Reconciliation | B11: Amount (£)
A12: Bank Statement Balance | B12: 852522.22
A13: Add: Deposits in Transit | B13: =SUM(C5:C7) -> 22000
A14: Less: Unpresented Payments | B14: =C8 -> 17000
A15: Adjusted Bank Balance | B15: =B12+B13-B14 -> 857522.22
A16: GL Bank Balance | B16: =SUMIF('Adjusted TB'!$A$4:$A$30,"1000",'Adjusted TB'!$H$4:$H$30) -> 857522.22
A17: Difference | B17: =B15-B16 -> 0

Sheet AR Ageing
A1: Accounts Receivable Ageing — 30 Sep 2026
A3: Invoice ID | B3: Customer | C3: Invoice Date | D3: Due Date | E3: Outstanding (£) | F3: Days Overdue | G3: Age Bucket | H3: Expected Credit Loss % | I3: ECL (£) | J3: Collection Priority | K3: Source
A4: AR0001 | B4: Customer 03 | C4: 46207 | D4: 46237 | E4: 14039.078 | F4: =DATE(2026,9,30)-D4 -> 58 | G4: =IF(F4<=0,"Current",IF(F4<=30,"1-30",IF(F4<=60,"31-60",IF(F4<=90,"61-90","90+")))) -> 31-60 | H4: =IF(G4="Current",0.5%,IF(G4="1-30",1%,IF(G4="31-60",3%,IF(G4="61-90",10%,25%)))) -> 0.03 | I4: =E4*H4 -> 421.17234 | J4: =IF(F4>90,"Escalate",IF(F4>30,"Chase","Routine")) -> Chase | K4: Synthetic AR ledger
A5: AR0002 | B5: Customer 26 | C5: 46272 | D5: 46302 | E5: 31470.479 | F5: =DATE(2026,9,30)-D5 -> -7 | G5: =IF(F5<=0,"Current",IF(F5<=30,"1-30",IF(F5<=60,"31-60",IF(F5<=90,"61-90","90+")))) -> Current | H5: =IF(G5="Current",0.5%,IF(G5="1-30",1%,IF(G5="31-60",3%,IF(G5="61-90",10%,25%)))) -> 0.005 | I5: =E5*H5 -> 157.35239 | J5: =IF(F5>90,"Escalate",IF(F5>30,"Chase","Routine")) -> Routine | K5: Synthetic AR ledger
A6: AR0003 | B6: Customer 06 | C6: 46266 | D6: 46296 | E6: 7983.4549 | F6: =DATE(2026,9,30)-D6 -> -1 | G6: =IF(F6<=0,"Current",IF(F6<=30,"1-30",IF(F6<=60,"31-60",IF(F6<=90,"61-90","90+")))) -> Current | H6: =IF(G6="Current",0.5%,IF(G6="1-30",1%,IF(G6="31-60",3%,IF(G6="61-90",10%,25%)))) -> 0.005 | I6: =E6*H6 -> 39.917275 | J6: =IF(F6>90,"Escalate",IF(F6>30,"Chase","Routine")) -> Routine | K6: Synthetic AR ledger
A7: AR0004 | B7: Customer 28 | C7: 46182 | D7: 46212 | E7: 15628.995 | F7: =DATE(2026,9,30)-D7 -> 83 | G7: =IF(F7<=0,"Current",IF(F7<=30,"1-30",IF(F7<=60,"31-60",IF(F7<=90,"61-90","90+")))) -> 61-90 | H7: =IF(G7="Current",0.5%,IF(G7="1-30",1%,IF(G7="31-60",3%,IF(G7="61-90",10%,25%)))) -> 0.1 | I7: =E7*H7 -> 1562.8995 | J7: =IF(F7>90,"Escalate",IF(F7>30,"Chase","Routine")) -> Chase | K7: Synthetic AR ledger
A8: AR0005 | B8: Customer 10 | C8: 46274 | D8: 46304 | E8: 15869.442 | F8: =DATE(2026,9,30)-D8 -> -9 | G8: =IF(F8<=0,"Current",IF(F8<=30,"1-30",IF(F8<=60,"31-60",IF(F8<=90,"61-90","90+")))) -> Current | H8: =IF(G8="Current",0.5%,IF(G8="1-30",1%,IF(G8="31-60",3%,IF(G8="61-90",10%,25%)))) -> 0.005 | I8: =E8*H8 -> 79.347212 | J8: =IF(F8>90,"Escalate",IF(F8>30,"Chase","Routine")) -> Routine | K8: Synthetic AR ledger
A9: AR0006 | B9: Customer 15 | C9: 46263 | D9: 46293 | E9: 31764.283 | F9: =DATE(2026,9,30)-D9 -> 2 | G9: =IF(F9<=0,"Current",IF(F9<=30,"1-30",IF(F9<=60,"31-60",IF(F9<=90,"61-90","90+")))) -> 1-30 | H9: =IF(G9="Current",0.5%,IF(G9="1-30",1%,IF(G9="31-60",3%,IF(G9="61-90",10%,25%)))) -> 0.01 | I9: =E9*H9 -> 317.64283 | J9: =IF(F9>90,"Escalate",IF(F9>30,"Chase","Routine")) -> Routine | K9: Synthetic AR ledger
A10: AR0007 | B10: Customer 04 | C10: 46267 | D10: 46297 | E10: 13557.091 | F10: =DATE(2026,9,30)-D10 -> -2 | G10: =IF(F10<=0,"Current",IF(F10<=30,"1-30",IF(F10<=60,"31-60",IF(F10<=90,"61-90","90+")))) -> Current | H10: =IF(G10="Current",0.5%,IF(G10="1-30",1%,IF(G10="31-60",3%,IF(G10="61-90",10%,25%)))) -> 0.005 | I10: =E10*H10 -> 67.785456 | J10: =IF(F10>90,"Escalate",IF(F10>30,"Chase","Routine")) -> Routine | K10: Synthetic AR ledger
A11: AR0008 | B11: Customer 22 | C11: 46284 | D11: 46314 | E11: 12017.833 | F11: =DATE(2026,9,30)-D11 -> -19 | G11: =IF(F11<=0,"Current",IF(F11<=30,"1-30",IF(F11<=60,"31-60",IF(F11<=90,"61-90","90+")))) -> Current | H11: =IF(G11="Current",0.5%,IF(G11="1-30",1%,IF(G11="31-60",3%,IF(G11="61-90",10%,25%)))) -> 0.005 | I11: =E11*H11 -> 60.089167 | J11: =IF(F11>90,"Escalate",IF(F11>30,"Chase","Routine")) -> Routine | K11: Synthetic AR ledger
A12: AR0009 | B12: Customer 10 | C12: 46178 | D12: 46208 | E12: 21988.504 | F12: =DATE(2026,9,30)-D12 -> 87 | G12: =IF(F12<=0,"Current",IF(F12<=30,"1-30",IF(F12<=60,"31-60",IF(F12<=90,"61-90","90+")))) -> 61-90 | H12: =IF(G12="Current",0.5%,IF(G12="1-30",1%,IF(G12="31-60",3%,IF(G12="61-90",10%,25%)))) -> 0.1 | I12: =E12*H12 -> 2198.8504 | J12: =IF(F12>90,"Escalate",IF(F12>30,"Chase","Routine")) -> Chase | K12: Synthetic AR ledger
A13: AR0010 | B13: Customer 05 | C13: 46281 | D13: 46311 | E13: 8647.2067 | F13: =DATE(2026,9,30)-D13 -> -16 | G13: =IF(F13<=0,"Current",IF(F13<=30,"1-30",IF(F13<=60,"31-60",IF(F13<=90,"61-90","90+")))) -> Current | H13: =IF(G13="Current",0.5%,IF(G13="1-30",1%,IF(G13="31-60",3%,IF(G13="61-90",10%,25%)))) -> 0.005 | I13: =E13*H13 -> 43.236034 | J13: =IF(F13>90,"Escalate",IF(F13>30,"Chase","Routine")) -> Routine | K13: Synthetic AR ledger
A14: AR0011 | B14: Customer 26 | C14: 46256 | D14: 46286 | E14: 13661.759 | F14: =DATE(2026,9,30)-D14 -> 9 | G14: =IF(F14<=0,"Current",IF(F14<=30,"1-30",IF(F14<=60,"31-60",IF(F14<=90,"61-90","90+")))) -> 1-30 | H14: =IF(G14="Current",0.5%,IF(G14="1-30",1%,IF(G14="31-60",3%,IF(G14="61-90",10%,25%)))) -> 0.01 | I14: =E14*H14 -> 136.61759 | J14: =IF(F14>90,"Escalate",IF(F14>30,"Chase","Routine")) -> Routine | K14: Synthetic AR ledger
A15: AR0012 | B15: Customer 07 | C15: 46259 | D15: 46289 | E15: 31918.29 | F15: =DATE(2026,9,30)-D15 -> 6 | G15: =IF(F15<=0,"Current",IF(F15<=30,"1-30",IF(F15<=60,"31-60",IF(F15<=90,"61-90","90+")))) -> 1-30 | H15: =IF(G15="Current",0.5%,IF(G15="1-30",1%,IF(G15="31-60",3%,IF(G15="61-90",10%,25%)))) -> 0.01 | I15: =E15*H15 -> 319.1829 | J15: =IF(F15>90,"Escalate",IF(F15>30,"Chase","Routine")) -> Routine | K15: Synthetic AR ledger
... A63: AR0060 | B63: Customer 27 | C63: 46283 | D63: 46313 | E63: 25068.763 | F63: =DATE(2026,9,30)-D63 -> -18 | G63: =IF(F63<=0,"Current",IF(F63<=30,"1-30",IF(F63<=60,"31-60",IF(F63<=90,"61-90","90+")))) -> Current | H63: =IF(G63="Current",0.5%,IF(G63="1-30",1%,IF(G63="31-60",3%,IF(G63="61-90",10%,25%)))) -> 0.005 | I63: =E63*H63 -> 125.34382 | J63: =IF(F63>90,"Escalate",IF(F63>30,"Chase","Routine")) -> Routine | K63: Synthetic AR ledger
A67: AR ageing summary
A68: Age Bucket | B68: Balance (£) | C68: % of AR | E68: Control | F68: Value
A69: Current | B69: =SUMIF(G4:G63,A69,E4:E63) -> 525125.68 | C69: =B69/$B$74 -> 0.45614513 | E69: AR Ledger Total | F69: =B74 -> 1151225
A70: 1-30 | B70: =SUMIF(G4:G63,A70,E4:E63) -> 300680.33 | C70: =B70/$B$74 -> 0.26118294 | E70: TB Trade Receivables | F70: =SUMIF('Adjusted TB'!$A$4:$A$30,"1100",'Adjusted TB'!$H$4:$H$30) -> 1151225
A71: 31-60 | B71: =SUMIF(G4:G63,A71,E4:E63) -> 214629.3 | C71: =B71/$B$74 -> 0.18643558 | E71: Difference | F71: =F69-F70 -> 0
A72: 61-90 | B72: =SUMIF(G4:G63,A72,E4:E63) -> 93403.796 | C72: =B72/$B$74 -> 0.081134267 | E72: Modelled ECL | F72: =SUM(I4:I63) -> 25758.165
A73: 90+ | B73: =SUMIF(G4:G63,A73,E4:E63) -> 17385.899 | C73: =B73/$B$74 -> 0.015102086
A74: TOTAL | B74: =SUM(E4:E63) -> 1151225 | C74: =SUM(C69:C73) -> 1

Sheet AP Ageing
A1: Accounts Payable Ageing — 30 Sep 2026
A3: Invoice ID | B3: Supplier | C3: Invoice Date | D3: Due Date | E3: Outstanding (£) | F3: Days Overdue | G3: Age Bucket | H3: Payment Priority | I3: Source
A4: AP0001 | B4: Supplier 18 | C4: 46245 | D4: 46275 | E4: 50864.075 | F4: =DATE(2026,9,30)-D4 -> 20 | G4: =IF(F4<=0,"Current",IF(F4<=30,"1-30",IF(F4<=60,"31-60",IF(F4<=90,"61-90","90+")))) -> 1-30 | H4: =IF(F4>60,"Urgent",IF(F4>30,"Schedule","Routine")) -> Routine | I4: Synthetic AP ledger
A5: AP0002 | B5: Supplier 08 | C5: 46278 | D5: 46308 | E5: 38483.994 | F5: =DATE(2026,9,30)-D5 -> -13 | G5: =IF(F5<=0,"Current",IF(F5<=30,"1-30",IF(F5<=60,"31-60",IF(F5<=90,"61-90","90+")))) -> Current | H5: =IF(F5>60,"Urgent",IF(F5>30,"Schedule","Routine")) -> Routine | I5: Synthetic AP ledger
A6: AP0003 | B6: Supplier 06 | C6: 46270 | D6: 46300 | E6: 15438.229 | F6: =DATE(2026,9,30)-D6 -> -5 | G6: =IF(F6<=0,"Current",IF(F6<=30,"1-30",IF(F6<=60,"31-60",IF(F6<=90,"61-90","90+")))) -> Current | H6: =IF(F6>60,"Urgent",IF(F6>30,"Schedule","Routine")) -> Routine | I6: Synthetic AP ledger
A7: AP0004 | B7: Supplier 17 | C7: 46286 | D7: 46316 | E7: 46383.742 | F7: =DATE(2026,9,30)-D7 -> -21 | G7: =IF(F7<=0,"Current",IF(F7<=30,"1-30",IF(F7<=60,"31-60",IF(F7<=90,"61-90","90+")))) -> Current | H7: =IF(F7>60,"Urgent",IF(F7>30,"Schedule","Routine")) -> Routine | I7: Synthetic AP ledger
A8: AP0005 | B8: Supplier 10 | C8: 46289 | D8: 46319 | E8: 12797.568 | F8: =DATE(2026,9,30)-D8 -> -24 | G8: =IF(F8<=0,"Current",IF(F8<=30,"1-30",IF(F8<=60,"31-60",IF(F8<=90,"61-90","90+")))) -> Current | H8: =IF(F8>60,"Urgent",IF(F8>30,"Schedule","Routine")) -> Routine | I8: Synthetic AP ledger
A9: AP0006 | B9: Supplier 14 | C9: 46272 | D9: 46302 | E9: 39524.212 | F9: =DATE(2026,9,30)-D9 -> -7 | G9: =IF(F9<=0,"Current",IF(F9<=30,"1-30",IF(F9<=60,"31-60",IF(F9<=90,"61-90","90+")))) -> Current | H9: =IF(F9>60,"Urgent",IF(F9>30,"Schedule","Routine")) -> Routine | I9: Synthetic AP ledger
A10: AP0007 | B10: Supplier 16 | C10: 46281 | D10: 46311 | E10: 13784.845 | F10: =DATE(2026,9,30)-D10 -> -16 | G10: =IF(F10<=0,"Current",IF(F10<=30,"1-30",IF(F10<=60,"31-60",IF(F10<=90,"61-90","90+")))) -> Current | H10: =IF(F10>60,"Urgent",IF(F10>30,"Schedule","Routine")) -> Routine | I10: Synthetic AP ledger
A11: AP0008 | B11: Supplier 01 | C11: 46275 | D11: 46305 | E11: 26360.363 | F11: =DATE(2026,9,30)-D11 -> -10 | G11: =IF(F11<=0,"Current",IF(F11<=30,"1-30",IF(F11<=60,"31-60",IF(F11<=90,"61-90","90+")))) -> Current | H11: =IF(F11>60,"Urgent",IF(F11>30,"Schedule","Routine")) -> Routine | I11: Synthetic AP ledger
A12: AP0009 | B12: Supplier 19 | C12: 46275 | D12: 46305 | E12: 46928.263 | F12: =DATE(2026,9,30)-D12 -> -10 | G12: =IF(F12<=0,"Current",IF(F12<=30,"1-30",IF(F12<=60,"31-60",IF(F12<=90,"61-90","90+")))) -> Current | H12: =IF(F12>60,"Urgent",IF(F12>30,"Schedule","Routine")) -> Routine | I12: Synthetic AP ledger
A13: AP0010 | B13: Supplier 03 | C13: 46197 | D13: 46227 | E13: 49684.766 | F13: =DATE(2026,9,30)-D13 -> 68 | G13: =IF(F13<=0,"Current",IF(F13<=30,"1-30",IF(F13<=60,"31-60",IF(F13<=90,"61-90","90+")))) -> 61-90 | H13: =IF(F13>60,"Urgent",IF(F13>30,"Schedule","Routine")) -> Urgent | I13: Synthetic AP ledger
A14: AP0011 | B14: Supplier 03 | C14: 46240 | D14: 46270 | E14: 51396.93 | F14: =DATE(2026,9,30)-D14 -> 25 | G14: =IF(F14<=0,"Current",IF(F14<=30,"1-30",IF(F14<=60,"31-60",IF(F14<=90,"61-90","90+")))) -> 1-30 | H14: =IF(F14>60,"Urgent",IF(F14>30,"Schedule","Routine")) -> Routine | I14: Synthetic AP ledger
A15: AP0012 | B15: Supplier 19 | C15: 46290 | D15: 46320 | E15: 48759.03 | F15: =DATE(2026,9,30)-D15 -> -25 | G15: =IF(F15<=0,"Current",IF(F15<=30,"1-30",IF(F15<=60,"31-60",IF(F15<=90,"61-90","90+")))) -> Current | H15: =IF(F15>60,"Urgent",IF(F15>30,"Schedule","Routine")) -> Routine | I15: Synthetic AP ledger
... A53: AP0050 | B53: Supplier 06 | C53: 46266 | D53: 46296 | E53: 30817.402 | F53: =DATE(2026,9,30)-D53 -> -1 | G53: =IF(F53<=0,"Current",IF(F53<=30,"1-30",IF(F53<=60,"31-60",IF(F53<=90,"61-90","90+")))) -> Current | H53: =IF(F53>60,"Urgent",IF(F53>30,"Schedule","Routine")) -> Routine | I53: Synthetic AP ledger
A57: AP ageing summary
A58: Age Bucket | B58: Balance (£) | C58: % of AP | E58: Control | F58: Value
A59: Current | B59: =SUMIF(G4:G53,A59,E4:E53) -> 915881.72 | C59: =B59/$B$64 -> 0.55848763 | E59: AP Ledger Total | F59: =B64 -> 1639932
A60: 1-30 | B60: =SUMIF(G4:G53,A60,E4:E53) -> 365172.52 | C60: =B60/$B$64 -> 0.22267541 | E60: TB Trade Payables | F60: =-SUMIF('Adjusted TB'!$A$4:$A$30,"2000",'Adjusted TB'!$H$4:$H$30) -> 1639932
A61: 31-60 | B61: =SUMIF(G4:G53,A61,E4:E53) -> 132176.99 | C61: =B61/$B$64 -> 0.080599071 | E61: Difference | F61: =F59-F60 -> 0
A62: 61-90 | B62: =SUMIF(G4:G53,A62,E4:E53) -> 166832.19 | C62: =B62/$B$64 -> 0.10173117
A63: 90+ | B63: =SUMIF(G4:G53,A63,E4:E53) -> 59868.53 | C63: =B63/$B$64 -> 0.036506716
A64: TOTAL | B64: =SUM(E4:E53) -> 1639932 | C64: =SUM(C59:C63) -> 1

Sheet Working Capital
A1: Working Capital & Cash Conversion Cycle
A3: Month | B3: Revenue (£) | C3: COGS (£) | D3: Trade Receivables (£) | E3: Inventory (£) | F3: Trade Payables (£) | G3: DSO | H3: Inventory Days | I3: DPO | J3: Cash Conversion Cycle | K3: Net Working Capital (£) | L3: NWC Change (£) | M3: Comment
A4: 46023 | B4: =-SUMIFS('GL Extract'!$I$4:$I$943,'GL Extract'!$C$4:$C$943,"4000",'GL Extract'!$B$4:$B$943,">="&DATE(2026,1,1),'GL Extract'!$B$4:$B$943,"<"&DATE(2026,2,1)) -> 820000 | C4: =SUMIFS('GL Extract'!$I$4:$I$943,'GL Extract'!$C$4:$C$943,"5000",'GL Extract'!$B$4:$B$943,">="&DATE(2026,1,1),'GL Extract'!$B$4:$B$943,"<"&DATE(2026,2,1)) -> 455100 | D4: =1*(SUMIF('Opening TB'!$A$4:$A$30,"1100",'Opening TB'!$C$4:$C$30)+SUMIFS('GL Extract'!$I$4:$I$943,'GL Extract'!$C$4:$C$943,"1100",'GL Extract'!$B$4:$B$943,"<"&DATE(2026,2,1))) -> 836900 | E4: =1*(SUMIF('Opening TB'!$A$4:$A$30,"1200",'Opening TB'!$C$4:$C$30)+SUMIFS('GL Extract'!$I$4:$I$943,'GL Extract'!$C$4:$C$943,"1200",'GL Extract'!$B$4:$B$943,"<"&DATE(2026,2,1))) -> 645449 | F4: =-1*(SUMIF('Opening TB'!$A$4:$A$30,"2000",'Opening TB'!$C$4:$C$30)+SUMIFS('GL Extract'!$I$4:$I$943,'GL Extract'!$C$4:$C$943,"2000",'GL Extract'!$B$4:$B$943,"<"&DATE(2026,2,1))) -> 709934.55 | G4: =IFERROR(D4/B4*30,0) -> 30.618293 | H4: =IFERROR(E4/C4*30,0) -> 42.547726 | I4: =IFERROR(F4/C4*30,0) -> 46.798586 | J4: =G4+H4-I4 -> 26.367432 | K4: =D4+E4-F4 -> 772414.45 | L4: - | M4: =IF(J4>75,"Working capital pressure",IF(J4<60,"Efficient conversion","Monitor")) -> Efficient conversion
A5: 46054 | B5: =-SUMIFS('GL Extract'!$I$4:$I$943,'GL Extract'!$C$4:$C$943,"4000",'GL Extract'!$B$4:$B$943,">="&DATE(2026,2,1),'GL Extract'!$B$4:$B$943,"<"&DATE(2026,3,1)) -> 845000 | C5: =SUMIFS('GL Extract'!$I$4:$I$943,'GL Extract'!$C$4:$C$943,"5000",'GL Extract'!$B$4:$B$943,">="&DATE(2026,2,1),'GL Extract'!$B$4:$B$943,"<"&DATE(2026,3,1)) -> 467285 | D5: =1*(SUMIF('Opening TB'!$A$4:$A$30,"1100",'Opening TB'!$C$4:$C$30)+SUMIFS('GL Extract'!$I$4:$I$943,'GL Extract'!$C$4:$C$943,"1100",'GL Extract'!$B$4:$B$943,"<"&DATE(2026,3,1))) -> 877460 | E5: =1*(SUMIF('Opening TB'!$A$4:$A$30,"1200",'Opening TB'!$C$4:$C$30)+SUMIFS('GL Extract'!$I$4:$I$943,'GL Extract'!$C$4:$C$943,"1200",'GL Extract'!$B$4:$B$943,"<"&DATE(2026,3,1))) -> 650121.85 | F5: =-1*(SUMIF('Opening TB'!$A$4:$A$30,"2000",'Opening TB'!$C$4:$C$30)+SUMIFS('GL Extract'!$I$4:$I$943,'GL Extract'!$C$4:$C$943,"2000",'GL Extract'!$B$4:$B$943,"<"&DATE(2026,3,1))) -> 825256.28 | G5: =IFERROR(D5/B5*30,0) -> 31.152426 | H5: =IFERROR(E5/C5*30,0) -> 41.738244 | I5: =IFERROR(F5/C5*30,0) -> 52.981989 | J5: =G5+H5-I5 -> 19.908682 | K5: =D5+E5-F5 -> 702325.57 | L5: =K5-K4 -> -70088.879 | M5: =IF(J5>75,"Working capital pressure",IF(J5<60,"Efficient conversion","Monitor")) -> Efficient conversion
A6: 46082 | B6: =-SUMIFS('GL Extract'!$I$4:$I$943,'GL Extract'!$C$4:$C$943,"4000",'GL Extract'!$B$4:$B$943,">="&DATE(2026,3,1),'GL Extract'!$B$4:$B$943,"<"&DATE(2026,4,1)) -> 875000 | C6: =SUMIFS('GL Extract'!$I$4:$I$943,'GL Extract'!$C$4:$C$943,"5000",'GL Extract'!$B$4:$B$943,">="&DATE(2026,3,1),'GL Extract'!$B$4:$B$943,"<"&DATE(2026,4,1)) -> 483000 | D6: =1*(SUMIF('Opening TB'!$A$4:$A$30,"1100",'Opening TB'!$C$4:$C$30)+SUMIFS('GL Extract'!$I$4:$I$943,'GL Extract'!$C$4:$C$943,"1100",'GL Extract'!$B$4:$B$943,"<"&DATE(2026,4,1))) -> 914210 | E6: =1*(SUMIF('Opening TB'!$A$4:$A$30,"1200",'Opening TB'!$C$4:$C$30)+SUMIFS('GL Extract'!$I$4:$I$943,'GL Extract'!$C$4:$C$943,"1200",'GL Extract'!$B$4:$B$943,"<"&DATE(2026,4,1))) -> 650121.85 | F6: =-1*(SUMIF('Opening TB'!$A$4:$A$30,"2000",'Opening TB'!$C$4:$C$30)+SUMIFS('GL Extract'!$I$4:$I$943,'GL Extract'!$C$4:$C$943,"2000",'GL Extract'!$B$4:$B$943,"<"&DATE(2026,4,1))) -> 937163.99 | G6: =IFERROR(D6/B6*30,0) -> 31.344343 | H6: =IFERROR(E6/C6*30,0) -> 40.380239 | I6: =IFERROR(F6/C6*30,0) -> 58.208943 | J6: =G6+H6-I6 -> 13.515639 | K6: =D6+E6-F6 -> 627167.86 | L6: =K6-K5 -> -75157.702 | M6: =IF(J6>75,"Working capital pressure",IF(J6<60,"Efficient conversion","Monitor")) -> Efficient conversion
A7: 46113 | B7: =-SUMIFS('GL Extract'!$I$4:$I$943,'GL Extract'!$C$4:$C$943,"4000",'GL Extract'!$B$4:$B$943,">="&DATE(2026,4,1),'GL Extract'!$B$4:$B$943,"<"&DATE(2026,5,1)) -> 900000 | C7: =SUMIFS('GL Extract'!$I$4:$I$943,'GL Extract'!$C$4:$C$943,"5000",'GL Extract'!$B$4:$B$943,">="&DATE(2026,4,1),'GL Extract'!$B$4:$B$943,"<"&DATE(2026,5,1)) -> 495000 | D7: =1*(SUMIF('Opening TB'!$A$4:$A$30,"1100",'Opening TB'!$C$4:$C$30)+SUMIFS('GL Extract'!$I$4:$I$943,'GL Extract'!$C$4:$C$943,"1100",'GL Extract'!$B$4:$B$943,"<"&DATE(2026,5,1))) -> 953810 | E7: =1*(SUMIF('Opening TB'!$A$4:$A$30,"1200",'Opening TB'!$C$4:$C$30)+SUMIFS('GL Extract'!$I$4:$I$943,'GL Extract'!$C$4:$C$943,"1200",'GL Extract'!$B$4:$B$943,"<"&DATE(2026,5,1))) -> 660021.85 | F7: =-1*(SUMIF('Opening TB'!$A$4:$A$30,"2000",'Opening TB'!$C$4:$C$30)+SUMIFS('GL Extract'!$I$4:$I$943,'GL Extract'!$C$4:$C$943,"2000",'GL Extract'!$B$4:$B$943,"<"&DATE(2026,5,1))) -> 1055762.8 | G7: =IFERROR(D7/B7*30,0) -> 31.793667 | H7: =IFERROR(E7/C7*30,0) -> 40.001324 | I7: =IFERROR(F7/C7*30,0) -> 63.985622 | J7: =G7+H7-I7 -> 7.8093693 | K7: =D7+E7-F7 -> 558069.09 | L7: =K7-K6 -> -69098.771 | M7: =IF(J7>75,"Working capital pressure",IF(J7<60,"Efficient conversion","Monitor")) -> Efficient conversion
A8: 46143 | B8: =-SUMIFS('GL Extract'!$I$4:$I$943,'GL Extract'!$C$4:$C$943,"4000",'GL Extract'!$B$4:$B$943,">="&DATE(2026,5,1),'GL Extract'!$B$4:$B$943,"<"&DATE(2026,6,1)) -> 930000 | C8: =SUMIFS('GL Extract'!$I$4:$I$943,'GL Extract'!$C$4:$C$943,"5000",'GL Extract'!$B$4:$B$943,">="&DATE(2026,5,1),'GL Extract'!$B$4:$B$943,"<"&DATE(2026,6,1)) -> 509640 | D8: =1*(SUMIF('Opening TB'!$A$4:$A$30,"1100",'Opening TB'!$C$4:$C$30)+SUMIFS('GL Extract'!$I$4:$I$943,'GL Extract'!$C$4:$C$943,"1100",'GL Extract'!$B$4:$B$943,"<"&DATE(2026,6,1))) -> 991010 | E8: =1*(SUMIF('Opening TB'!$A$4:$A$30,"1200",'Opening TB'!$C$4:$C$30)+SUMIFS('GL Extract'!$I$4:$I$943,'GL Extract'!$C$4:$C$943,"1200",'GL Extract'!$B$4:$B$943,"<"&DATE(2026,6,1))) -> 660021.85 | F8: =-1*(SUMIF('Opening TB'!$A$4:$A$30,"2000",'Opening TB'!$C$4:$C$30)+SUMIFS('GL Extract'!$I$4:$I$943,'GL Extract'!$C$4:$C$943,"2000",'GL Extract'!$B$4:$B$943,"<"&DATE(2026,6,1))) -> 1174077.4 | G8: =IFERROR(D8/B8*30,0) -> 31.968065 | H8: =IFERROR(E8/C8*30,0) -> 38.85224 | I8: =IFERROR(F8/C8*30,0) -> 69.112162 | J8: =G8+H8-I8 -> 1.7081424 | K8: =D8+E8-F8 -> 476954.44 | L8: =K8-K7 -> -81114.651 | M8: =IF(J8>75,"Working capital pressure",IF(J8<60,"Efficient conversion","Monitor")) -> Efficient conversion
A9: 46174 | B9: =-SUMIFS('GL Extract'!$I$4:$I$943,'GL Extract'!$C$4:$C$943,"4000",'GL Extract'!$B$4:$B$943,">="&DATE(2026,6,1),'GL Extract'!$B$4:$B$943,"<"&DATE(2026,7,1)) -> 955000 | C9: =SUMIFS('GL Extract'!$I$4:$I$943,'GL Extract'!$C$4:$C$943,"5000",'GL Extract'!$B$4:$B$943,">="&DATE(2026,6,1),'GL Extract'!$B$4:$B$943,"<"&DATE(2026,7,1)) -> 524295 | D9: =1*(SUMIF('Opening TB'!$A$4:$A$30,"1100",'Opening TB'!$C$4:$C$30)+SUMIFS('GL Extract'!$I$4:$I$943,'GL Extract'!$C$4:$C$943,"1100",'GL Extract'!$B$4:$B$943,"<"&DATE(2026,7,1))) -> 1031120 | E9: =1*(SUMIF('Opening TB'!$A$4:$A$30,"1200",'Opening TB'!$C$4:$C$30)+SUMIFS('GL Extract'!$I$4:$I$943,'GL Extract'!$C$4:$C$943,"1200",'GL Extract'!$B$4:$B$943,"<"&DATE(2026,7,1))) -> 654778.9 | F9: =-1*(SUMIF('Opening TB'!$A$4:$A$30,"2000",'Opening TB'!$C$4:$C$30)+SUMIFS('GL Extract'!$I$4:$I$943,'GL Extract'!$C$4:$C$943,"2000",'GL Extract'!$B$4:$B$943,"<"&DATE(2026,7,1))) -> 1300461.5 | G9: =IFERROR(D9/B9*30,0) -> 32.391204 | H9: =IFERROR(E9/C9*30,0) -> 37.466249 | I9: =IFERROR(F9/C9*30,0) -> 74.412008 | J9: =G9+H9-I9 -> -4.5545548 | K9: =D9+E9-F9 -> 385437.44 | L9: =K9-K8 -> -91517 | M9: =IF(J9>75,"Working capital pressure",IF(J9<60,"Efficient conversion","Monitor")) -> Efficient conversion
A10: 46204 | B10: =-SUMIFS('GL Extract'!$I$4:$I$943,'GL Extract'!$C$4:$C$943,"4000",'GL Extract'!$B$4:$B$943,">="&DATE(2026,7,1),'GL Extract'!$B$4:$B$943,"<"&DATE(2026,8,1)) -> 970000 | C10: =SUMIFS('GL Extract'!$I$4:$I$943,'GL Extract'!$C$4:$C$943,"5000",'GL Extract'!$B$4:$B$943,">="&DATE(2026,7,1),'GL Extract'!$B$4:$B$943,"<"&DATE(2026,8,1)) -> 530590 | D10: =1*(SUMIF('Opening TB'!$A$4:$A$30,"1100",'Opening TB'!$C$4:$C$30)+SUMIFS('GL Extract'!$I$4:$I$943,'GL Extract'!$C$4:$C$943,"1100",'GL Extract'!$B$4:$B$943,"<"&DATE(2026,8,1))) -> 1067980 | E10: =1*(SUMIF('Opening TB'!$A$4:$A$30,"1200",'Opening TB'!$C$4:$C$30)+SUMIFS('GL Extract'!$I$4:$I$943,'GL Extract'!$C$4:$C$943,"1200",'GL Extract'!$B$4:$B$943,"<"&DATE(2026,8,1))) -> 660084.8 | F10: =-1*(SUMIF('Opening TB'!$A$4:$A$30,"2000",'Opening TB'!$C$4:$C$30)+SUMIFS('GL Extract'!$I$4:$I$943,'GL Extract'!$C$4:$C$943,"2000",'GL Extract'!$B$4:$B$943,"<"&DATE(2026,8,1))) -> 1421566.2 | G10: =IFERROR(D10/B10*30,0) -> 33.030309 | H10: =IFERROR(E10/C10*30,0) -> 37.321744 | I10: =IFERROR(F10/C10*30,0) -> 80.376536 | J10: =G10+H10-I10 -> -10.024483 | K10: =D10+E10-F10 -> 306498.58 | L10: =K10-K9 -> -78938.859 | M10: =IF(J10>75,"Working capital pressure",IF(J10<60,"Efficient conversion","Monitor")) -> Efficient conversion
A11: 46235 | B11: =-SUMIFS('GL Extract'!$I$4:$I$943,'GL Extract'!$C$4:$C$943,"4000",'GL Extract'!$B$4:$B$943,">="&DATE(2026,8,1),'GL Extract'!$B$4:$B$943,"<"&DATE(2026,9,1)) -> 990000 | C11: =SUMIFS('GL Extract'!$I$4:$I$943,'GL Extract'!$C$4:$C$943,"5000",'GL Extract'!$B$4:$B$943,">="&DATE(2026,8,1),'GL Extract'!$B$4:$B$943,"<"&DATE(2026,9,1)) -> 540540 | D11: =1*(SUMIF('Opening TB'!$A$4:$A$30,"1100",'Opening TB'!$C$4:$C$30)+SUMIFS('GL Extract'!$I$4:$I$943,'GL Extract'!$C$4:$C$943,"1100",'GL Extract'!$B$4:$B$943,"<"&DATE(2026,9,1))) -> 1107580 | E11: =1*(SUMIF('Opening TB'!$A$4:$A$30,"1200",'Opening TB'!$C$4:$C$30)+SUMIFS('GL Extract'!$I$4:$I$943,'GL Extract'!$C$4:$C$943,"1200",'GL Extract'!$B$4:$B$943,"<"&DATE(2026,9,1))) -> 660084.8 | F11: =-1*(SUMIF('Opening TB'!$A$4:$A$30,"2000",'Opening TB'!$C$4:$C$30)+SUMIFS('GL Extract'!$I$4:$I$943,'GL Extract'!$C$4:$C$943,"2000",'GL Extract'!$B$4:$B$943,"<"&DATE(2026,9,1))) -> 1550593.2 | G11: =IFERROR(D11/B11*30,0) -> 33.56303 | H11: =IFERROR(E11/C11*30,0) -> 36.634743 | I11: =IFERROR(F11/C11*30,0) -> 86.058007 | J11: =G11+H11-I11 -> -15.860234 | K11: =D11+E11-F11 -> 217071.63 | L11: =K11-K10 -> -89426.957 | M11: =IF(J11>75,"Working capital pressure",IF(J11<60,"Efficient conversion","Monitor")) -> Efficient conversion
A12: 46266 | B12: =-SUMIFS('GL Extract'!$I$4:$I$943,'GL Extract'!$C$4:$C$943,"4000",'GL Extract'!$B$4:$B$943,">="&DATE(2026,9,1),'GL Extract'!$B$4:$B$943,"<"&DATE(2026,10,1)) -> 1015000 | C12: =SUMIFS('GL Extract'!$I$4:$I$943,'GL Extract'!$C$4:$C$943,"5000",'GL Extract'!$B$4:$B$943,">="&DATE(2026,9,1),'GL Extract'!$B$4:$B$943,"<"&DATE(2026,10,1)) -> 553175 | D12: =1*(SUMIF('Opening TB'!$A$4:$A$30,"1100",'Opening TB'!$C$4:$C$30)+SUMIFS('GL Extract'!$I$4:$I$943,'GL Extract'!$C$4:$C$943,"1100",'GL Extract'!$B$4:$B$943,"<"&DATE(2026,10,1))+SUMIF('Adjustment Journals'!$C$4:$C$17,"1100",'Adjustment Journals'!$H$4:$H$17)) -> 1151225 | E12: =1*(SUMIF('Opening TB'!$A$4:$A$30,"1200",'Opening TB'!$C$4:$C$30)+SUMIFS('GL Extract'!$I$4:$I$943,'GL Extract'!$C$4:$C$943,"1200",'GL Extract'!$B$4:$B$943,"<"&DATE(2026,10,1))+SUMIF('Adjustment Journals'!$C$4:$C$17,"1200",'Adjustment Journals'!$H$4:$H$17)) -> 660084.8 | F12: =-1*(SUMIF('Opening TB'!$A$4:$A$30,"2000",'Opening TB'!$C$4:$C$30)+SUMIFS('GL Extract'!$I$4:$I$943,'GL Extract'!$C$4:$C$943,"2000",'GL Extract'!$B$4:$B$943,"<"&DATE(2026,10,1))+SUMIF('Adjustment Journals'!$C$4:$C$17,"2000",'Adjustment Journals'!$H$4:$H$17)) -> 1639932 | G12: =IFERROR(D12/B12*30,0) -> 34.026355 | H12: =IFERROR(E12/C12*30,0) -> 35.797974 | I12: =IFERROR(F12/C12*30,0) -> 88.937422 | J12: =G12+H12-I12 -> -19.113094 | K12: =D12+E12-F12 -> 171377.84 | L12: =K12-K11 -> -45693.783 | M12: =IF(J12>75,"Working capital pressure",IF(J12<60,"Efficient conversion","Monitor")) -> Efficient conversion
A15: September working-capital snapshot
A16: Metric | B16: Sep-26
A17: DSO | B17: =G12 -> 34.026355
A18: Inventory Days | B18: =H12 -> 35.797974
A19: DPO | B19: =I12 -> 88.937422
A20: Cash Conversion Cycle | B20: =J12 -> -19.113094
A21: Net Working Capital | B21: =K12 -> 171377.84
A22: 90+ Day AR % | B22: ='AR Ageing'!C73 -> 0.015102086

Sheet 13-Week Cash Forecast
A1: 13-Week Cash Forecast — Q4 2026
A3: Week 1 starts Monday 5 Oct 2026 | synthetic collection and payment assumptions
A5: Week | B5: Week Start | C5: Customer Receipts (£) | D5: Supplier Payments (£) | E5: Payroll (£) | F5: Rent (£) | G5: Other Opex (£) | H5: Capex (£) | I5: Tax / Interest (£) | J5: Net Cash Flow (£) | K5: Opening Cash (£) | L5: Ending Cash (£) | M5: Policy Floor (£) | N5: Headroom (£) | O5: Status | Q5: Week Start | R5: Ending Cash
A6: 1 | B6: 46300 | C6: =Assumptions!$B$7*Assumptions!$B$8+('AR Ageing'!$B$74*0.24) -> 494374 | D6: =Assumptions!$B$9*Assumptions!$B$10+('AP Ageing'!$B$64*0.22) -> 484265.03 | E6: =Assumptions!$B$11*0 -> 0 | F6: =Assumptions!$B$12*1 -> 52000 | G6: =Assumptions!$B$13 -> 27000 | H6: 0 | I6: 0 | J6: =C6-D6-E6-F6-G6-H6-I6 -> -68891.03 | K6: =SUMIF('Adjusted TB'!$A$4:$A$30,"1000",'Adjusted TB'!$H$4:$H$30) -> 857522.22 | L6: =K6+J6 -> 788631.19 | M6: =Assumptions!$B$14 -> 250000 | N6: =L6-M6 -> 538631.19 | O6: =IF(N6<0,"Below policy",IF(N6<100000,"Tight","Above policy")) -> Above policy | Q6: 46300 | R6: =L6 -> 788631.19
A7: 2 | B7: 46307 | C7: =Assumptions!$B$7*Assumptions!$B$8+('AR Ageing'!$B$74*0.22) -> 471349.5 | D7: =Assumptions!$B$9*Assumptions!$B$10+('AP Ageing'!$B$64*0.2) -> 451466.39 | E7: =Assumptions!$B$11*0 -> 0 | F7: =Assumptions!$B$12*0 -> 0 | G7: =Assumptions!$B$13 -> 27000 | H7: 0 | I7: 0 | J7: =C7-D7-E7-F7-G7-H7-I7 -> -7116.8913 | K7: =L6 -> 788631.19 | L7: =K7+J7 -> 781514.3 | M7: =Assumptions!$B$14 -> 250000 | N7: =L7-M7 -> 531514.3 | O7: =IF(N7<0,"Below policy",IF(N7<100000,"Tight","Above policy")) -> Above policy | Q7: 46307 | R7: =L7 -> 781514.3
A8: 3 | B8: 46314 | C8: =Assumptions!$B$7*Assumptions!$B$8+('AR Ageing'!$B$74*0.18) -> 425300.5 | D8: =Assumptions!$B$9*Assumptions!$B$10+('AP Ageing'!$B$64*0.18) -> 418667.75 | E8: =Assumptions!$B$11*0 -> 0 | F8: =Assumptions!$B$12*0 -> 0 | G8: =Assumptions!$B$13 -> 27000 | H8: 0 | I8: 0 | J8: =C8-D8-E8-F8-G8-H8-I8 -> -20367.252 | K8: =L7 -> 781514.3 | L8: =K8+J8 -> 761147.05 | M8: =Assumptions!$B$14 -> 250000 | N8: =L8-M8 -> 511147.05 | O8: =IF(N8<0,"Below policy",IF(N8<100000,"Tight","Above policy")) -> Above policy | Q8: 46314 | R8: =L8 -> 761147.05
A9: 4 | B9: 46321 | C9: =Assumptions!$B$7*Assumptions!$B$8+('AR Ageing'!$B$74*0.12) -> 356227 | D9: =Assumptions!$B$9*Assumptions!$B$10+('AP Ageing'!$B$64*0.14) -> 353070.47 | E9: =Assumptions!$B$11*1 -> 215000 | F9: =Assumptions!$B$12*0 -> 0 | G9: =Assumptions!$B$13 -> 27000 | H9: 0 | I9: 0 | J9: =C9-D9-E9-F9-G9-H9-I9 -> -238843.47 | K9: =L8 -> 761147.05 | L9: =K9+J9 -> 522303.57 | M9: =Assumptions!$B$14 -> 250000 | N9: =L9-M9 -> 272303.57 | O9: =IF(N9<0,"Below policy",IF(N9<100000,"Tight","Above policy")) -> Above policy | Q9: 46321 | R9: =L9 -> 522303.57
A10: 5 | B10: 46328 | C10: =Assumptions!$B$7*Assumptions!$B$8+('AR Ageing'!$B$74*0) -> 218080 | D10: =Assumptions!$B$9*Assumptions!$B$10+('AP Ageing'!$B$64*0) -> 123480 | E10: =Assumptions!$B$11*0 -> 0 | F10: =Assumptions!$B$12*1 -> 52000 | G10: =Assumptions!$B$13 -> 27000 | H10: 0 | I10: 0 | J10: =C10-D10-E10-F10-G10-H10-I10 -> 15600 | K10: =L9 -> 522303.57 | L10: =K10+J10 -> 537903.57 | M10: =Assumptions!$B$14 -> 250000 | N10: =L10-M10 -> 287903.57 | O10: =IF(N10<0,"Below policy",IF(N10<100000,"Tight","Above policy")) -> Above policy | Q10: 46328 | R10: =L10 -> 537903.57
A11: 6 | B11: 46335 | C11: =Assumptions!$B$7*Assumptions!$B$8+('AR Ageing'!$B$74*0) -> 218080 | D11: =Assumptions!$B$9*Assumptions!$B$10+('AP Ageing'!$B$64*0) -> 123480 | E11: =Assumptions!$B$11*0 -> 0 | F11: =Assumptions!$B$12*0 -> 0 | G11: =Assumptions!$B$13 -> 27000 | H11: 45000 | I11: 0 | J11: =C11-D11-E11-F11-G11-H11-I11 -> 22600 | K11: =L10 -> 537903.57 | L11: =K11+J11 -> 560503.57 | M11: =Assumptions!$B$14 -> 250000 | N11: =L11-M11 -> 310503.57 | O11: =IF(N11<0,"Below policy",IF(N11<100000,"Tight","Above policy")) -> Above policy | Q11: 46335 | R11: =L11 -> 560503.57
A12: 7 | B12: 46342 | C12: =Assumptions!$B$7*Assumptions!$B$8+('AR Ageing'!$B$74*0) -> 218080 | D12: =Assumptions!$B$9*Assumptions!$B$10+('AP Ageing'!$B$64*0) -> 123480 | E12: =Assumptions!$B$11*0 -> 0 | F12: =Assumptions!$B$12*0 -> 0 | G12: =Assumptions!$B$13 -> 27000 | H12: 0 | I12: 0 | J12: =C12-D12-E12-F12-G12-H12-I12 -> 67600 | K12: =L11 -> 560503.57 | L12: =K12+J12 -> 628103.57 | M12: =Assumptions!$B$14 -> 250000 | N12: =L12-M12 -> 378103.57 | O12: =IF(N12<0,"Below policy",IF(N12<100000,"Tight","Above policy")) -> Above policy | Q12: 46342 | R12: =L12 -> 628103.57
A13: 8 | B13: 46349 | C13: =Assumptions!$B$7*Assumptions!$B$8+('AR Ageing'!$B$74*0) -> 218080 | D13: =Assumptions!$B$9*Assumptions!$B$10+('AP Ageing'!$B$64*0) -> 123480 | E13: =Assumptions!$B$11*1 -> 215000 | F13: =Assumptions!$B$12*0 -> 0 | G13: =Assumptions!$B$13 -> 27000 | H13: 0 | I13: 0 | J13: =C13-D13-E13-F13-G13-H13-I13 -> -147400 | K13: =L12 -> 628103.57 | L13: =K13+J13 -> 480703.57 | M13: =Assumptions!$B$14 -> 250000 | N13: =L13-M13 -> 230703.57 | O13: =IF(N13<0,"Below policy",IF(N13<100000,"Tight","Above policy")) -> Above policy | Q13: 46349 | R13: =L13 -> 480703.57
A14: 9 | B14: 46356 | C14: =Assumptions!$B$7*Assumptions!$B$8+('AR Ageing'!$B$74*0) -> 218080 | D14: =Assumptions!$B$9*Assumptions!$B$10+('AP Ageing'!$B$64*0) -> 123480 | E14: =Assumptions!$B$11*0 -> 0 | F14: =Assumptions!$B$12*1 -> 52000 | G14: =Assumptions!$B$13 -> 27000 | H14: 0 | I14: 0 | J14: =C14-D14-E14-F14-G14-H14-I14 -> 15600 | K14: =L13 -> 480703.57 | L14: =K14+J14 -> 496303.57 | M14: =Assumptions!$B$14 -> 250000 | N14: =L14-M14 -> 246303.57 | O14: =IF(N14<0,"Below policy",IF(N14<100000,"Tight","Above policy")) -> Above policy | Q14: 46356 | R14: =L14 -> 496303.57
A15: 10 | B15: 46363 | C15: =Assumptions!$B$7*Assumptions!$B$8+('AR Ageing'!$B$74*0) -> 218080 | D15: =Assumptions!$B$9*Assumptions!$B$10+('AP Ageing'!$B$64*0) -> 123480 | E15: =Assumptions!$B$11*0 -> 0 | F15: =Assumptions!$B$12*0 -> 0 | G15: =Assumptions!$B$13 -> 27000 | H15: 0 | I15: 60000 | J15: =C15-D15-E15-F15-G15-H15-I15 -> 7600 | K15: =L14 -> 496303.57 | L15: =K15+J15 -> 503903.57 | M15: =Assumptions!$B$14 -> 250000 | N15: =L15-M15 -> 253903.57 | O15: =IF(N15<0,"Below policy",IF(N15<100000,"Tight","Above policy")) -> Above policy | Q15: 46363 | R15: =L15 -> 503903.57
A16: 11 | B16: 46370 | C16: =Assumptions!$B$7*Assumptions!$B$8+('AR Ageing'!$B$74*0) -> 218080 | D16: =Assumptions!$B$9*Assumptions!$B$10+('AP Ageing'!$B$64*0) -> 123480 | E16: =Assumptions!$B$11*0 -> 0 | F16: =Assumptions!$B$12*0 -> 0 | G16: =Assumptions!$B$13 -> 27000 | H16: 45000 | I16: 0 | J16: =C16-D16-E16-F16-G16-H16-I16 -> 22600 | K16: =L15 -> 503903.57 | L16: =K16+J16 -> 526503.57 | M16: =Assumptions!$B$14 -> 250000 | N16: =L16-M16 -> 276503.57 | O16: =IF(N16<0,"Below policy",IF(N16<100000,"Tight","Above policy")) -> Above policy | Q16: 46370 | R16: =L16 -> 526503.57
A17: 12 | B17: 46377 | C17: =Assumptions!$B$7*Assumptions!$B$8+('AR Ageing'!$B$74*0) -> 218080 | D17: =Assumptions!$B$9*Assumptions!$B$10+('AP Ageing'!$B$64*0) -> 123480 | E17: =Assumptions!$B$11*0 -> 0 | F17: =Assumptions!$B$12*0 -> 0 | G17: =Assumptions!$B$13 -> 27000 | H17: 0 | I17: 0 | J17: =C17-D17-E17-F17-G17-H17-I17 -> 67600 | K17: =L16 -> 526503.57 | L17: =K17+J17 -> 594103.57 | M17: =Assumptions!$B$14 -> 250000 | N17: =L17-M17 -> 344103.57 | O17: =IF(N17<0,"Below policy",IF(N17<100000,"Tight","Above policy")) -> Above policy | Q17: 46377 | R17: =L17 -> 594103.57
A18: 13 | B18: 46384 | C18: =Assumptions!$B$7*Assumptions!$B$8+('AR Ageing'!$B$74*0) -> 218080 | D18: =Assumptions!$B$9*Assumptions!$B$10+('AP Ageing'!$B$64*0) -> 123480 | E18: =Assumptions!$B$11*1 -> 215000 | F18: =Assumptions!$B$12*1 -> 52000 | G18: =Assumptions!$B$13 -> 27000 | H18: 0 | I18: 0 | J18: =C18-D18-E18-F18-G18-H18-I18 -> -199400 | K18: =L17 -> 594103.57 | L18: =K18+J18 -> 394703.57 | M18: =Assumptions!$B$14 -> 250000 | N18: =L18-M18 -> 144703.57 | O18: =IF(N18<0,"Below policy",IF(N18<100000,"Tight","Above policy")) -> Above policy | Q18: 46384 | R18: =L18 -> 394703.57
A21: Liquidity summary
A22: Metric | B22: Value
A23: Opening Cash | B23: =K6 -> 857522.22
A24: Minimum Cash | B24: =MIN(L6:L18) -> 394703.57
A25: Week 13 Ending Cash | B25: =L18 -> 394703.57
A26: Minimum Headroom | B26: =MIN(N6:N18) -> 144703.57

Sheet Month-End Close
A1: September 2026 Month-End Close Checklist
A3: Task # | B3: Close Task | C3: Owner | D3: Due Date | E3: Status | F3: Evidence Sheet | G3: Evidence / Comment | H3: Completion % | I3: RAG | J3: Control
A4: 1 | B4: Freeze sales ledger and review cut-off | C4: Financial Accountant | D4: 46296 | E4: Complete | F4: GL Extract | G4: Revenue cut-off reviewed | H4: =IF(E4="Complete",100%,IF(E4="In progress",50%,0%)) -> 1 | I4: =IF(E4="Complete","Green",IF(DATE(2026,10,3)>D4,"Red","Amber")) -> Green | J4: =IF(E4="Complete","Done",IF(DATE(2026,10,3)>D4,"Overdue","Open")) -> Done
A5: 2 | B5: Freeze purchase ledger and review cut-off | C5: AP Lead | D5: 46296 | E5: Complete | F5: GL Extract | G5: Supplier cut-off reviewed | H5: =IF(E5="Complete",100%,IF(E5="In progress",50%,0%)) -> 1 | I5: =IF(E5="Complete","Green",IF(DATE(2026,10,3)>D5,"Red","Amber")) -> Green | J5: =IF(E5="Complete","Done",IF(DATE(2026,10,3)>D5,"Overdue","Open")) -> Done
A6: 3 | B6: Reconcile bank account | C6: Financial Accountant | D6: 46297 | E6: Complete | F6: Bank Reconciliation | G6: Difference = £0 | H6: =IF(E6="Complete",100%,IF(E6="In progress",50%,0%)) -> 1 | I6: =IF(E6="Complete","Green",IF(DATE(2026,10,3)>D6,"Red","Amber")) -> Green | J6: =IF(E6="Complete","Done",IF(DATE(2026,10,3)>D6,"Overdue","Open")) -> Done
A7: 4 | B7: Reconcile trade receivables | C7: Credit Controller | D7: 46297 | E7: Complete | F7: AR Ageing | G7: Ledger ties to TB | H7: =IF(E7="Complete",100%,IF(E7="In progress",50%,0%)) -> 1 | I7: =IF(E7="Complete","Green",IF(DATE(2026,10,3)>D7,"Red","Amber")) -> Green | J7: =IF(E7="Complete","Done",IF(DATE(2026,10,3)>D7,"Overdue","Open")) -> Done
A8: 5 | B8: Review aged debt and bad-debt provision | C8: Finance Business Partner | D8: 46297 | E8: In progress | F8: AR Ageing | G8: ECL review | H8: =IF(E8="Complete",100%,IF(E8="In progress",50%,0%)) -> 0.5 | I8: =IF(E8="Complete","Green",IF(DATE(2026,10,3)>D8,"Red","Amber")) -> Red | J8: =IF(E8="Complete","Done",IF(DATE(2026,10,3)>D8,"Overdue","Open")) -> Overdue
A9: 6 | B9: Reconcile trade payables | C9: AP Lead | D9: 46297 | E9: Complete | F9: AP Ageing | G9: Ledger ties to TB | H9: =IF(E9="Complete",100%,IF(E9="In progress",50%,0%)) -> 1 | I9: =IF(E9="Complete","Green",IF(DATE(2026,10,3)>D9,"Red","Amber")) -> Green | J9: =IF(E9="Complete","Done",IF(DATE(2026,10,3)>D9,"Overdue","Open")) -> Done
A10: 7 | B10: Prepare accruals | C10: Management Accountant | D10: 46297 | E10: Complete | F10: Adjustment Journals | G10: Utilities / professional / marketing | H10: =IF(E10="Complete",100%,IF(E10="In progress",50%,0%)) -> 1 | I10: =IF(E10="Complete","Green",IF(DATE(2026,10,3)>D10,"Red","Amber")) -> Green | J10: =IF(E10="Complete","Done",IF(DATE(2026,10,3)>D10,"Overdue","Open")) -> Done
A11: 8 | B11: Prepare prepayments | C11: Management Accountant | D11: 46297 | E11: Complete | F11: Adjustment Journals | G11: Insurance prepayment | H11: =IF(E11="Complete",100%,IF(E11="In progress",50%,0%)) -> 1 | I11: =IF(E11="Complete","Green",IF(DATE(2026,10,3)>D11,"Red","Amber")) -> Green | J11: =IF(E11="Complete","Done",IF(DATE(2026,10,3)>D11,"Overdue","Open")) -> Done
A12: 9 | B12: Post depreciation | C12: Management Accountant | D12: 46297 | E12: Complete | F12: Adjustment Journals | G12: September depreciation | H12: =IF(E12="Complete",100%,IF(E12="In progress",50%,0%)) -> 1 | I12: =IF(E12="Complete","Green",IF(DATE(2026,10,3)>D12,"Red","Amber")) -> Green | J12: =IF(E12="Complete","Done",IF(DATE(2026,10,3)>D12,"Overdue","Open")) -> Done
A13: 10 | B13: Review payroll / bonus accrual | C13: Finance Manager | D13: 46297 | E13: Complete | F13: Adjustment Journals | G13: Q3 bonus accrual | H13: =IF(E13="Complete",100%,IF(E13="In progress",50%,0%)) -> 1 | I13: =IF(E13="Complete","Green",IF(DATE(2026,10,3)>D13,"Red","Amber")) -> Green | J13: =IF(E13="Complete","Done",IF(DATE(2026,10,3)>D13,"Overdue","Open")) -> Done
A14: 11 | B14: Review adjusted trial balance | C14: Finance Manager | D14: 46298 | E14: In progress | F14: Adjusted TB | G14: TB balances | H14: =IF(E14="Complete",100%,IF(E14="In progress",50%,0%)) -> 0.5 | I14: =IF(E14="Complete","Green",IF(DATE(2026,10,3)>D14,"Red","Amber")) -> Amber | J14: =IF(E14="Complete","Done",IF(DATE(2026,10,3)>D14,"Overdue","Open")) -> Open
A15: 12 | B15: Prepare management P&L | C15: Management Accountant | D15: 46298 | E15: In progress | F15: Management P&L | G15: Actual vs budget | H15: =IF(E15="Complete",100%,IF(E15="In progress",50%,0%)) -> 0.5 | I15: =IF(E15="Complete","Green",IF(DATE(2026,10,3)>D15,"Red","Amber")) -> Amber | J15: =IF(E15="Complete","Done",IF(DATE(2026,10,3)>D15,"Overdue","Open")) -> Open
... A19: 16 | B19: Final management review / sign-off | C19: CFO | D19: 46300 | E19: Not started | F19: Dashboard | G19: Final pack sign-off | H19: =IF(E19="Complete",100%,IF(E19="In progress",50%,0%)) -> 0 | I19: =IF(E19="Complete","Green",IF(DATE(2026,10,3)>D19,"Red","Amber")) -> Amber | J19: =IF(E19="Complete","Done",IF(DATE(2026,10,3)>D19,"Overdue","Open")) -> Open
A22: Close status summary
A23: Metric | B23: Value
A24: Tasks Complete | B24: =COUNTIF(E4:E19,"Complete") -> 9
A25: Tasks In Progress | B25: =COUNTIF(E4:E19,"In progress") -> 3
A26: Tasks Not Started | B26: =COUNTIF(E4:E19,"Not started") -> 4
A27: Overall Completion | B27: =AVERAGE(H4:H19) -> 0.65625

Sheet Dashboard
A1: Finance Operations Dashboard — September 2026 Close
A3: Month-end close | management accounts | working capital | liquidity
A5: YTD Revenue | D5: YTD EBITDA | G5: Sep Closing Cash | J5: Cash Conversion Cycle
A6: ='Management P&L'!K4 -> 8300000 | D6: ='Management P&L'!K18 -> -7599.9369 | G6: ='Balance Sheet'!C4 -> 857522.22 | J6: ='Working Capital'!B20 -> -19.113094
A9: 90+ Day AR % | D9: Bank Rec Difference | G9: Week 13 Cash | J9: Close Completion
A10: ='Working Capital'!B22 -> 0.015102086 | D10: ='Bank Reconciliation'!B17 -> 0 | G10: ='13-Week Cash Forecast'!B25 -> 394703.57 | J10: ='Month-End Close'!B27 -> 0.65625
A14: Monthly Revenue & EBITDA
A15: Month | B15: Revenue (£) | C15: EBITDA (£)
A16: Jan-26 | B16: ='Management P&L'!B4 -> 820000 | C16: ='Management P&L'!B18 -> -117287.97
A17: Feb-26 | B17: ='Management P&L'!C4 -> 845000 | C17: ='Management P&L'!C18 -> -14123.132
A18: Mar-26 | B18: ='Management P&L'!D4 -> 875000 | C18: ='Management P&L'!D18 -> 2566.1378
A19: Apr-26 | B19: ='Management P&L'!E4 -> 900000 | C19: ='Management P&L'!E18 -> 10905.935
A20: May-26 | B20: ='Management P&L'!F4 -> 930000 | C20: ='Management P&L'!F18 -> 20506.903
A21: Jun-26 | B21: ='Management P&L'!G4 -> 955000 | C21: ='Management P&L'!G18 -> 21072.307
A22: Jul-26 | B22: ='Management P&L'!H4 -> 970000 | C22: ='Management P&L'!H18 -> 35344.347
A23: Aug-26 | B23: ='Management P&L'!I4 -> 990000 | C23: ='Management P&L'!I18 -> 30192.228
A24: Sep-26 | B24: ='Management P&L'!J4 -> 1015000 | C24: ='Management P&L'!J18 -> 3223.3062
A34: Working Capital Days
A35: Month | B35: DSO | C35: Inventory Days | D35: DPO
A36: Jan-26 | B36: ='Working Capital'!G4 -> 30.618293 | C36: ='Working Capital'!H4 -> 42.547726 | D36: ='Working Capital'!I4 -> 46.798586
A37: Feb-26 | B37: ='Working Capital'!G5 -> 31.152426 | C37: ='Working Capital'!H5 -> 41.738244 | D37: ='Working Capital'!I5 -> 52.981989
A38: Mar-26 | B38: ='Working Capital'!G6 -> 31.344343 | C38: ='Working Capital'!H6 -> 40.380239 | D38: ='Working Capital'!I6 -> 58.208943
A39: Apr-26 | B39: ='Working Capital'!G7 -> 31.793667 | C39: ='Working Capital'!H7 -> 40.001324 | D39: ='Working Capital'!I7 -> 63.985622
A40: May-26 | B40: ='Working Capital'!G8 -> 31.968065 | C40: ='Working Capital'!H8 -> 38.85224 | D40: ='Working Capital'!I8 -> 69.112162
A41: Jun-26 | B41: ='Working Capital'!G9 -> 32.391204 | C41: ='Working Capital'!H9 -> 37.466249 | D41: ='Working Capital'!I9 -> 74.412008
A42: Jul-26 | B42: ='Working Capital'!G10 -> 33.030309 | C42: ='Working Capital'!H10 -> 37.321744 | D42: ='Working Capital'!I10 -> 80.376536
A43: Aug-26 | B43: ='Working Capital'!G11 -> 33.56303 | C43: ='Working Capital'!H11 -> 36.634743 | D43: ='Working Capital'!I11 -> 86.058007
A44: Sep-26 | B44: ='Working Capital'!G12 -> 34.026355 | C44: ='Working Capital'!H12 -> 35.797974 | D44: ='Working Capital'!I12 -> 88.937422
A53: Finance manager focus areas
A54: 1 | B54: Complete remaining close-review tasks and obtain final CFO sign-off.
A55: 2 | B55: Escalate 90+ day receivables and compare modelled ECL with the posted bad-debt allowance.
A56: 3 | B56: Monitor the cash-conversion cycle and avoid inventory growth outpacing sales.
A57: 4 | B57: Use the 13-week cash forecast to schedule supplier payments and planned Q4 capex.
A58: 5 | B58: Maintain reconciliation controls: bank, AR and AP must tie back to the adjusted trial balance.

Sheet Data Dictionary
A1: Data Dictionary & Accounting Definitions
A3: Metric | B3: Definition | C3: Unit | D3: Type | E3: Primary Sheet | F3: Finance Relevance | G3: Source / Note
A4: Adjusted Trial Balance | B4: Opening balance + base GL + month-end adjustments | C4: £ | D4: Formula | E4: Adjusted TB | F4: Core close control | G4: Synthetic ledger
A5: Accrual | B5: Expense recognised before supplier invoice receipt | C5: £ | D5: Adjustment | E5: Adjustment Journals | F5: Cut-off / completeness | G5: Synthetic estimate
A6: Prepayment | B6: Cash paid but expense relates to future period | C6: £ | D6: Adjustment | E6: Adjustment Journals | F6: Matching principle | G6: Synthetic schedule
A7: DSO | B7: Trade receivables / monthly revenue × 30 | C7: days | D7: Formula | E7: Working Capital | F7: Collections efficiency | G7: Modelled
A8: DPO | B8: Trade payables / monthly COGS × 30 | C8: days | D8: Formula | E8: Working Capital | F8: Supplier-payment timing | G8: Modelled
A9: Inventory Days | B9: Inventory / monthly COGS × 30 | C9: days | D9: Formula | E9: Working Capital | F9: Inventory efficiency | G9: Modelled
A10: Cash Conversion Cycle | B10: DSO + Inventory Days − DPO | C10: days | D10: Formula | E10: Working Capital | F10: Working-capital efficiency | G10: Modelled
A11: 13-Week Cash Forecast | B11: Weekly cash receipts less operating and planned cash outflows | C11: £ | D11: Forecast | E11: 13-Week Cash Forecast | F11: Liquidity planning | G11: Synthetic assumptions
A12: Bank Rec Difference | B12: Adjusted bank statement less GL cash | C12: £ | D12: Formula | E12: Bank Reconciliation | F12: Cash control | G12: Should equal zero
A13: ECL | B13: Outstanding AR × ageing-based loss rate | C13: £ | D13: Formula | E13: AR Ageing | F13: Receivables risk screen | G13: Synthetic rates
